package com.facebook.android.maps.a;

final class al
  extends aa
{
  al(am paramam) {}
  
  /* Error */
  public final void run()
  {
    // Byte code:
    //   0: aconst_null
    //   1: astore_3
    //   2: aconst_null
    //   3: astore 4
    //   5: aconst_null
    //   6: astore 5
    //   8: aconst_null
    //   9: astore 7
    //   11: aload_0
    //   12: getfield 10	com/facebook/android/maps/a/al:a	Lcom/facebook/android/maps/a/am;
    //   15: invokestatic 22	com/facebook/android/maps/a/am:a	(Lcom/facebook/android/maps/a/am;)Ljava/lang/String;
    //   18: invokestatic 28	android/graphics/BitmapFactory:decodeFile	(Ljava/lang/String;)Landroid/graphics/Bitmap;
    //   21: astore 6
    //   23: aload 6
    //   25: astore_2
    //   26: aload 6
    //   28: ifnonnull +119 -> 147
    //   31: new 30	java/net/URL
    //   34: dup
    //   35: aload_0
    //   36: getfield 10	com/facebook/android/maps/a/al:a	Lcom/facebook/android/maps/a/am;
    //   39: invokestatic 33	com/facebook/android/maps/a/am:b	(Lcom/facebook/android/maps/a/am;)Ljava/lang/String;
    //   42: invokespecial 36	java/net/URL:<init>	(Ljava/lang/String;)V
    //   45: invokevirtual 40	java/net/URL:openStream	()Ljava/io/InputStream;
    //   48: astore_2
    //   49: aload 7
    //   51: astore_3
    //   52: aload 5
    //   54: astore 4
    //   56: aload_0
    //   57: getfield 10	com/facebook/android/maps/a/al:a	Lcom/facebook/android/maps/a/am;
    //   60: invokestatic 44	com/facebook/android/maps/a/am:c	(Lcom/facebook/android/maps/a/am;)Landroid/content/Context;
    //   63: ldc 46
    //   65: iconst_0
    //   66: invokevirtual 52	android/content/Context:openFileOutput	(Ljava/lang/String;I)Ljava/io/FileOutputStream;
    //   69: astore 5
    //   71: aload 5
    //   73: astore_3
    //   74: aload 5
    //   76: astore 4
    //   78: sipush 2048
    //   81: newarray <illegal type>
    //   83: astore 7
    //   85: aload 5
    //   87: astore_3
    //   88: aload 5
    //   90: astore 4
    //   92: aload_2
    //   93: aload 7
    //   95: invokevirtual 58	java/io/InputStream:read	([B)I
    //   98: istore_1
    //   99: iload_1
    //   100: iconst_m1
    //   101: if_icmpeq +59 -> 160
    //   104: aload 5
    //   106: astore_3
    //   107: aload 5
    //   109: astore 4
    //   111: aload 5
    //   113: aload 7
    //   115: iconst_0
    //   116: iload_1
    //   117: invokevirtual 64	java/io/OutputStream:write	([BII)V
    //   120: goto -35 -> 85
    //   123: astore 4
    //   125: aload_2
    //   126: ifnull +7 -> 133
    //   129: aload_2
    //   130: invokevirtual 67	java/io/InputStream:close	()V
    //   133: aload 6
    //   135: astore_2
    //   136: aload_3
    //   137: ifnull +10 -> 147
    //   140: aload_3
    //   141: invokevirtual 68	java/io/OutputStream:close	()V
    //   144: aload 6
    //   146: astore_2
    //   147: new 70	com/facebook/android/maps/a/ak
    //   150: dup
    //   151: aload_0
    //   152: aload_2
    //   153: invokespecial 73	com/facebook/android/maps/a/ak:<init>	(Lcom/facebook/android/maps/a/al;Landroid/graphics/Bitmap;)V
    //   156: invokestatic 79	com/facebook/android/maps/a/ad:d	(Lcom/facebook/android/maps/a/aa;)V
    //   159: return
    //   160: aload 5
    //   162: astore_3
    //   163: aload 5
    //   165: astore 4
    //   167: aload 5
    //   169: invokevirtual 82	java/io/OutputStream:flush	()V
    //   172: aload 5
    //   174: astore_3
    //   175: aload 5
    //   177: astore 4
    //   179: aload 5
    //   181: invokevirtual 68	java/io/OutputStream:close	()V
    //   184: aload 5
    //   186: astore_3
    //   187: aload 5
    //   189: astore 4
    //   191: aload_0
    //   192: getfield 10	com/facebook/android/maps/a/al:a	Lcom/facebook/android/maps/a/am;
    //   195: invokestatic 22	com/facebook/android/maps/a/am:a	(Lcom/facebook/android/maps/a/am;)Ljava/lang/String;
    //   198: invokestatic 28	android/graphics/BitmapFactory:decodeFile	(Ljava/lang/String;)Landroid/graphics/Bitmap;
    //   201: astore 7
    //   203: aload 7
    //   205: astore_3
    //   206: aload_2
    //   207: ifnull +7 -> 214
    //   210: aload_2
    //   211: invokevirtual 67	java/io/InputStream:close	()V
    //   214: aload_3
    //   215: astore_2
    //   216: aload 5
    //   218: ifnull -71 -> 147
    //   221: aload 5
    //   223: invokevirtual 68	java/io/OutputStream:close	()V
    //   226: aload_3
    //   227: astore_2
    //   228: goto -81 -> 147
    //   231: astore_2
    //   232: aload_3
    //   233: astore_2
    //   234: goto -87 -> 147
    //   237: astore_3
    //   238: aconst_null
    //   239: astore_2
    //   240: aload_2
    //   241: ifnull +7 -> 248
    //   244: aload_2
    //   245: invokevirtual 67	java/io/InputStream:close	()V
    //   248: aload 4
    //   250: ifnull +8 -> 258
    //   253: aload 4
    //   255: invokevirtual 68	java/io/OutputStream:close	()V
    //   258: aload_3
    //   259: athrow
    //   260: astore_2
    //   261: goto -47 -> 214
    //   264: astore_2
    //   265: goto -132 -> 133
    //   268: astore_2
    //   269: aload 6
    //   271: astore_2
    //   272: goto -125 -> 147
    //   275: astore_2
    //   276: goto -28 -> 248
    //   279: astore_2
    //   280: goto -22 -> 258
    //   283: astore_3
    //   284: goto -44 -> 240
    //   287: astore_2
    //   288: aconst_null
    //   289: astore_2
    //   290: goto -165 -> 125
    // Local variable table:
    //   start	length	slot	name	signature
    //   0	293	0	this	al
    //   98	19	1	i	int
    //   25	203	2	localObject1	Object
    //   231	1	2	localIOException1	java.io.IOException
    //   233	12	2	localObject2	Object
    //   260	1	2	localIOException2	java.io.IOException
    //   264	1	2	localIOException3	java.io.IOException
    //   268	1	2	localIOException4	java.io.IOException
    //   271	1	2	localBitmap1	android.graphics.Bitmap
    //   275	1	2	localIOException5	java.io.IOException
    //   279	1	2	localIOException6	java.io.IOException
    //   287	1	2	localIOException7	java.io.IOException
    //   289	1	2	localObject3	Object
    //   1	232	3	localObject4	Object
    //   237	22	3	localObject5	Object
    //   283	1	3	localObject6	Object
    //   3	107	4	localObject7	Object
    //   123	1	4	localIOException8	java.io.IOException
    //   165	89	4	localObject8	Object
    //   6	216	5	localFileOutputStream	java.io.FileOutputStream
    //   21	249	6	localBitmap2	android.graphics.Bitmap
    //   9	195	7	localObject9	Object
    // Exception table:
    //   from	to	target	type
    //   56	71	123	java/io/IOException
    //   78	85	123	java/io/IOException
    //   92	99	123	java/io/IOException
    //   111	120	123	java/io/IOException
    //   167	172	123	java/io/IOException
    //   179	184	123	java/io/IOException
    //   191	203	123	java/io/IOException
    //   221	226	231	java/io/IOException
    //   31	49	237	finally
    //   210	214	260	java/io/IOException
    //   129	133	264	java/io/IOException
    //   140	144	268	java/io/IOException
    //   244	248	275	java/io/IOException
    //   253	258	279	java/io/IOException
    //   56	71	283	finally
    //   78	85	283	finally
    //   92	99	283	finally
    //   111	120	283	finally
    //   167	172	283	finally
    //   179	184	283	finally
    //   191	203	283	finally
    //   31	49	287	java/io/IOException
  }
}

/* Location:
 * Qualified Name:     com.facebook.android.maps.a.al
 * Java Class Version: 6 (50.0)
 * JD-Core Version:    0.7.1
 */