package com.instagram.feed.j;

import android.content.Context;

final class l
  implements Runnable
{
  private Context b;
  
  public l(o paramo, Context paramContext)
  {
    b = paramContext;
  }
  
  /* Error */
  public final void run()
  {
    // Byte code:
    //   0: aload_0
    //   1: getfield 19	com/instagram/feed/j/l:b	Landroid/content/Context;
    //   4: invokestatic 31	com/instagram/feed/j/o:c	(Landroid/content/Context;)Ljava/io/File;
    //   7: astore 4
    //   9: aload 4
    //   11: invokevirtual 37	java/io/File:exists	()Z
    //   14: ifeq +63 -> 77
    //   17: new 39	java/io/BufferedReader
    //   20: dup
    //   21: new 41	java/io/FileReader
    //   24: dup
    //   25: aload 4
    //   27: invokespecial 44	java/io/FileReader:<init>	(Ljava/io/File;)V
    //   30: invokespecial 47	java/io/BufferedReader:<init>	(Ljava/io/Reader;)V
    //   33: astore_2
    //   34: aload_2
    //   35: astore_1
    //   36: aload_2
    //   37: invokevirtual 51	java/io/BufferedReader:readLine	()Ljava/lang/String;
    //   40: astore_3
    //   41: aload_2
    //   42: astore_1
    //   43: aload_2
    //   44: invokevirtual 51	java/io/BufferedReader:readLine	()Ljava/lang/String;
    //   47: astore 5
    //   49: aload_2
    //   50: astore_1
    //   51: aload_0
    //   52: getfield 14	com/instagram/feed/j/l:a	Lcom/instagram/feed/j/o;
    //   55: getfield 54	com/instagram/feed/j/o:b	Landroid/os/Handler;
    //   58: new 56	com/instagram/feed/j/k
    //   61: dup
    //   62: aload_0
    //   63: aload_3
    //   64: aload 5
    //   66: invokespecial 59	com/instagram/feed/j/k:<init>	(Lcom/instagram/feed/j/l;Ljava/lang/String;Ljava/lang/String;)V
    //   69: invokevirtual 65	android/os/Handler:post	(Ljava/lang/Runnable;)Z
    //   72: pop
    //   73: aload_2
    //   74: invokevirtual 68	java/io/BufferedReader:close	()V
    //   77: return
    //   78: astore_1
    //   79: ldc 70
    //   81: ldc 72
    //   83: aload_1
    //   84: invokestatic 77	com/facebook/e/a/a:b	(Ljava/lang/String;Ljava/lang/String;Ljava/lang/Throwable;)V
    //   87: return
    //   88: astore_3
    //   89: aconst_null
    //   90: astore_2
    //   91: aload_2
    //   92: astore_1
    //   93: ldc 70
    //   95: ldc 79
    //   97: aload_3
    //   98: invokestatic 77	com/facebook/e/a/a:b	(Ljava/lang/String;Ljava/lang/String;Ljava/lang/Throwable;)V
    //   101: aload_2
    //   102: ifnull -25 -> 77
    //   105: aload_2
    //   106: invokevirtual 68	java/io/BufferedReader:close	()V
    //   109: return
    //   110: astore_1
    //   111: ldc 70
    //   113: ldc 72
    //   115: aload_1
    //   116: invokestatic 77	com/facebook/e/a/a:b	(Ljava/lang/String;Ljava/lang/String;Ljava/lang/Throwable;)V
    //   119: return
    //   120: astore_3
    //   121: aconst_null
    //   122: astore_2
    //   123: aload_2
    //   124: astore_1
    //   125: aload 4
    //   127: invokevirtual 82	java/io/File:delete	()Z
    //   130: pop
    //   131: aload_2
    //   132: astore_1
    //   133: ldc 70
    //   135: ldc 84
    //   137: aload_3
    //   138: invokestatic 77	com/facebook/e/a/a:b	(Ljava/lang/String;Ljava/lang/String;Ljava/lang/Throwable;)V
    //   141: aload_2
    //   142: ifnull -65 -> 77
    //   145: aload_2
    //   146: invokevirtual 68	java/io/BufferedReader:close	()V
    //   149: return
    //   150: astore_1
    //   151: ldc 70
    //   153: ldc 72
    //   155: aload_1
    //   156: invokestatic 77	com/facebook/e/a/a:b	(Ljava/lang/String;Ljava/lang/String;Ljava/lang/Throwable;)V
    //   159: return
    //   160: astore_2
    //   161: aconst_null
    //   162: astore_1
    //   163: aload_1
    //   164: ifnull +7 -> 171
    //   167: aload_1
    //   168: invokevirtual 68	java/io/BufferedReader:close	()V
    //   171: aload_2
    //   172: athrow
    //   173: astore_1
    //   174: ldc 70
    //   176: ldc 72
    //   178: aload_1
    //   179: invokestatic 77	com/facebook/e/a/a:b	(Ljava/lang/String;Ljava/lang/String;Ljava/lang/Throwable;)V
    //   182: goto -11 -> 171
    //   185: astore_2
    //   186: goto -23 -> 163
    //   189: astore_3
    //   190: goto -67 -> 123
    //   193: astore_3
    //   194: goto -103 -> 91
    // Local variable table:
    //   start	length	slot	name	signature
    //   0	197	0	this	l
    //   35	16	1	localBufferedReader1	java.io.BufferedReader
    //   78	6	1	localIOException1	java.io.IOException
    //   92	1	1	localBufferedReader2	java.io.BufferedReader
    //   110	6	1	localIOException2	java.io.IOException
    //   124	9	1	localBufferedReader3	java.io.BufferedReader
    //   150	6	1	localIOException3	java.io.IOException
    //   162	6	1	localObject1	Object
    //   173	6	1	localIOException4	java.io.IOException
    //   33	113	2	localBufferedReader4	java.io.BufferedReader
    //   160	12	2	localObject2	Object
    //   185	1	2	localObject3	Object
    //   40	24	3	str1	String
    //   88	10	3	localFileNotFoundException1	java.io.FileNotFoundException
    //   120	18	3	localIOException5	java.io.IOException
    //   189	1	3	localIOException6	java.io.IOException
    //   193	1	3	localFileNotFoundException2	java.io.FileNotFoundException
    //   7	119	4	localFile	java.io.File
    //   47	18	5	str2	String
    // Exception table:
    //   from	to	target	type
    //   73	77	78	java/io/IOException
    //   17	34	88	java/io/FileNotFoundException
    //   105	109	110	java/io/IOException
    //   17	34	120	java/io/IOException
    //   145	149	150	java/io/IOException
    //   17	34	160	finally
    //   167	171	173	java/io/IOException
    //   36	41	185	finally
    //   43	49	185	finally
    //   51	73	185	finally
    //   93	101	185	finally
    //   125	131	185	finally
    //   133	141	185	finally
    //   36	41	189	java/io/IOException
    //   43	49	189	java/io/IOException
    //   51	73	189	java/io/IOException
    //   36	41	193	java/io/FileNotFoundException
    //   43	49	193	java/io/FileNotFoundException
    //   51	73	193	java/io/FileNotFoundException
  }
}

/* Location:
 * Qualified Name:     com.instagram.feed.j.l
 * Java Class Version: 6 (50.0)
 * JD-Core Version:    0.7.1
 */