package com.instagram.feed.j;

import android.content.Context;

public final class m
  implements Runnable
{
  private Context b;
  
  public m(o paramo, Context paramContext)
  {
    b = paramContext;
  }
  
  /* Error */
  public final void run()
  {
    // Byte code:
    //   0: aload_0
    //   1: getfield 19	com/instagram/feed/j/m:b	Landroid/content/Context;
    //   4: invokestatic 31	com/instagram/feed/j/o:c	(Landroid/content/Context;)Ljava/io/File;
    //   7: astore_1
    //   8: new 33	java/io/BufferedWriter
    //   11: dup
    //   12: new 35	java/io/FileWriter
    //   15: dup
    //   16: aload_1
    //   17: invokespecial 38	java/io/FileWriter:<init>	(Ljava/io/File;)V
    //   20: invokespecial 41	java/io/BufferedWriter:<init>	(Ljava/io/Writer;)V
    //   23: astore_2
    //   24: aload_2
    //   25: astore_1
    //   26: aload_2
    //   27: aload_0
    //   28: getfield 14	com/instagram/feed/j/m:a	Lcom/instagram/feed/j/o;
    //   31: invokevirtual 44	com/instagram/feed/j/o:a	()Ljava/lang/String;
    //   34: invokevirtual 48	java/io/BufferedWriter:write	(Ljava/lang/String;)V
    //   37: aload_2
    //   38: astore_1
    //   39: aload_2
    //   40: invokevirtual 51	java/io/BufferedWriter:newLine	()V
    //   43: aload_2
    //   44: astore_1
    //   45: aload_2
    //   46: aload_0
    //   47: getfield 14	com/instagram/feed/j/m:a	Lcom/instagram/feed/j/o;
    //   50: invokevirtual 53	com/instagram/feed/j/o:b	()Ljava/lang/String;
    //   53: invokevirtual 48	java/io/BufferedWriter:write	(Ljava/lang/String;)V
    //   56: aload_2
    //   57: invokevirtual 56	java/io/BufferedWriter:close	()V
    //   60: return
    //   61: astore_1
    //   62: ldc 58
    //   64: ldc 60
    //   66: aload_1
    //   67: invokestatic 65	com/facebook/e/a/a:b	(Ljava/lang/String;Ljava/lang/String;Ljava/lang/Throwable;)V
    //   70: return
    //   71: astore_3
    //   72: aconst_null
    //   73: astore_2
    //   74: aload_2
    //   75: astore_1
    //   76: ldc 58
    //   78: ldc 67
    //   80: aload_3
    //   81: invokestatic 65	com/facebook/e/a/a:b	(Ljava/lang/String;Ljava/lang/String;Ljava/lang/Throwable;)V
    //   84: aload_2
    //   85: ifnull -25 -> 60
    //   88: aload_2
    //   89: invokevirtual 56	java/io/BufferedWriter:close	()V
    //   92: return
    //   93: astore_1
    //   94: ldc 58
    //   96: ldc 60
    //   98: aload_1
    //   99: invokestatic 65	com/facebook/e/a/a:b	(Ljava/lang/String;Ljava/lang/String;Ljava/lang/Throwable;)V
    //   102: return
    //   103: astore_3
    //   104: aconst_null
    //   105: astore_2
    //   106: aload_2
    //   107: astore_1
    //   108: ldc 58
    //   110: ldc 69
    //   112: aload_3
    //   113: invokestatic 65	com/facebook/e/a/a:b	(Ljava/lang/String;Ljava/lang/String;Ljava/lang/Throwable;)V
    //   116: aload_2
    //   117: ifnull -57 -> 60
    //   120: aload_2
    //   121: invokevirtual 56	java/io/BufferedWriter:close	()V
    //   124: return
    //   125: astore_1
    //   126: ldc 58
    //   128: ldc 60
    //   130: aload_1
    //   131: invokestatic 65	com/facebook/e/a/a:b	(Ljava/lang/String;Ljava/lang/String;Ljava/lang/Throwable;)V
    //   134: return
    //   135: astore_2
    //   136: aconst_null
    //   137: astore_1
    //   138: aload_1
    //   139: ifnull +7 -> 146
    //   142: aload_1
    //   143: invokevirtual 56	java/io/BufferedWriter:close	()V
    //   146: aload_2
    //   147: athrow
    //   148: astore_1
    //   149: ldc 58
    //   151: ldc 60
    //   153: aload_1
    //   154: invokestatic 65	com/facebook/e/a/a:b	(Ljava/lang/String;Ljava/lang/String;Ljava/lang/Throwable;)V
    //   157: goto -11 -> 146
    //   160: astore_2
    //   161: goto -23 -> 138
    //   164: astore_3
    //   165: goto -59 -> 106
    //   168: astore_3
    //   169: goto -95 -> 74
    // Local variable table:
    //   start	length	slot	name	signature
    //   0	172	0	this	m
    //   7	38	1	localObject1	Object
    //   61	6	1	localIOException1	java.io.IOException
    //   75	1	1	localObject2	Object
    //   93	6	1	localIOException2	java.io.IOException
    //   107	1	1	localObject3	Object
    //   125	6	1	localIOException3	java.io.IOException
    //   137	6	1	localObject4	Object
    //   148	6	1	localIOException4	java.io.IOException
    //   23	98	2	localBufferedWriter	java.io.BufferedWriter
    //   135	12	2	localObject5	Object
    //   160	1	2	localObject6	Object
    //   71	10	3	localFileNotFoundException1	java.io.FileNotFoundException
    //   103	10	3	localIOException5	java.io.IOException
    //   164	1	3	localIOException6	java.io.IOException
    //   168	1	3	localFileNotFoundException2	java.io.FileNotFoundException
    // Exception table:
    //   from	to	target	type
    //   56	60	61	java/io/IOException
    //   8	24	71	java/io/FileNotFoundException
    //   88	92	93	java/io/IOException
    //   8	24	103	java/io/IOException
    //   120	124	125	java/io/IOException
    //   8	24	135	finally
    //   142	146	148	java/io/IOException
    //   26	37	160	finally
    //   39	43	160	finally
    //   45	56	160	finally
    //   76	84	160	finally
    //   108	116	160	finally
    //   26	37	164	java/io/IOException
    //   39	43	164	java/io/IOException
    //   45	56	164	java/io/IOException
    //   26	37	168	java/io/FileNotFoundException
    //   39	43	168	java/io/FileNotFoundException
    //   45	56	168	java/io/FileNotFoundException
  }
}

/* Location:
 * Qualified Name:     com.instagram.feed.j.m
 * Java Class Version: 6 (50.0)
 * JD-Core Version:    0.7.1
 */