package com.instagram.explore.b;

public final class j
{
  /* Error */
  public static String a(Iterable<com.instagram.explore.model.j> paramIterable)
  {
    // Byte code:
    //   0: new 12	java/io/StringWriter
    //   3: dup
    //   4: invokespecial 16	java/io/StringWriter:<init>	()V
    //   7: astore_2
    //   8: getstatic 21	com/instagram/common/h/a:a	Lcom/a/a/a/e;
    //   11: aload_2
    //   12: invokevirtual 26	com/a/a/a/e:a	(Ljava/io/Writer;)Lcom/a/a/a/k;
    //   15: astore_3
    //   16: aconst_null
    //   17: astore_1
    //   18: aload_3
    //   19: invokevirtual 31	com/a/a/a/k:b	()V
    //   22: aload_0
    //   23: invokeinterface 37 1 0
    //   28: astore_0
    //   29: aload_0
    //   30: invokeinterface 43 1 0
    //   35: ifeq +46 -> 81
    //   38: aload_3
    //   39: aload_0
    //   40: invokeinterface 47 1 0
    //   45: checkcast 49	com/instagram/explore/model/j
    //   48: getfield 53	com/instagram/explore/model/j:f	Ljava/lang/String;
    //   51: invokevirtual 56	com/a/a/a/k:b	(Ljava/lang/String;)V
    //   54: goto -25 -> 29
    //   57: astore_1
    //   58: aload_1
    //   59: athrow
    //   60: astore_0
    //   61: aload_3
    //   62: ifnull +11 -> 73
    //   65: aload_1
    //   66: ifnull +39 -> 105
    //   69: aload_3
    //   70: invokevirtual 59	com/a/a/a/k:close	()V
    //   73: aload_0
    //   74: athrow
    //   75: astore_0
    //   76: aload_2
    //   77: invokevirtual 63	java/io/StringWriter:toString	()Ljava/lang/String;
    //   80: areturn
    //   81: aload_3
    //   82: invokevirtual 66	com/a/a/a/k:c	()V
    //   85: aload_3
    //   86: ifnull -10 -> 76
    //   89: aload_3
    //   90: invokevirtual 59	com/a/a/a/k:close	()V
    //   93: goto -17 -> 76
    //   96: astore_3
    //   97: aload_1
    //   98: aload_3
    //   99: invokestatic 71	com/facebook/a/a:a	(Ljava/lang/Throwable;Ljava/lang/Throwable;)V
    //   102: goto -29 -> 73
    //   105: aload_3
    //   106: invokevirtual 59	com/a/a/a/k:close	()V
    //   109: goto -36 -> 73
    //   112: astore_0
    //   113: goto -52 -> 61
    // Local variable table:
    //   start	length	slot	name	signature
    //   0	116	0	paramIterable	Iterable<com.instagram.explore.model.j>
    //   17	1	1	localObject	Object
    //   57	41	1	localThrowable1	Throwable
    //   7	70	2	localStringWriter	java.io.StringWriter
    //   15	75	3	localk	com.a.a.a.k
    //   96	10	3	localThrowable2	Throwable
    // Exception table:
    //   from	to	target	type
    //   18	29	57	java/lang/Throwable
    //   29	54	57	java/lang/Throwable
    //   81	85	57	java/lang/Throwable
    //   58	60	60	finally
    //   8	16	75	java/io/IOException
    //   69	73	75	java/io/IOException
    //   73	75	75	java/io/IOException
    //   89	93	75	java/io/IOException
    //   97	102	75	java/io/IOException
    //   105	109	75	java/io/IOException
    //   69	73	96	java/lang/Throwable
    //   18	29	112	finally
    //   29	54	112	finally
    //   81	85	112	finally
  }
  
  /* Error */
  public static String a(java.util.List<com.instagram.explore.model.RelatedItem> paramList)
  {
    // Byte code:
    //   0: new 12	java/io/StringWriter
    //   3: dup
    //   4: invokespecial 16	java/io/StringWriter:<init>	()V
    //   7: astore_2
    //   8: getstatic 21	com/instagram/common/h/a:a	Lcom/a/a/a/e;
    //   11: aload_2
    //   12: invokevirtual 26	com/a/a/a/e:a	(Ljava/io/Writer;)Lcom/a/a/a/k;
    //   15: astore_3
    //   16: aconst_null
    //   17: astore_1
    //   18: aload_3
    //   19: invokevirtual 31	com/a/a/a/k:b	()V
    //   22: aload_0
    //   23: invokeinterface 78 1 0
    //   28: astore 4
    //   30: aload 4
    //   32: invokeinterface 43 1 0
    //   37: ifeq +122 -> 159
    //   40: aload 4
    //   42: invokeinterface 47 1 0
    //   47: checkcast 80	com/instagram/explore/model/RelatedItem
    //   50: astore 5
    //   52: getstatic 85	com/instagram/explore/model/l:a	[I
    //   55: aload 5
    //   57: invokevirtual 88	com/instagram/explore/model/RelatedItem:a	()Lcom/instagram/explore/model/j;
    //   60: invokevirtual 92	com/instagram/explore/model/j:ordinal	()I
    //   63: iaload
    //   64: tableswitch	default:+130->194, 1:+86->150
    //   84: aload 5
    //   86: getfield 94	com/instagram/explore/model/RelatedItem:a	Ljava/lang/String;
    //   89: astore_0
    //   90: aload 5
    //   92: invokevirtual 88	com/instagram/explore/model/RelatedItem:a	()Lcom/instagram/explore/model/j;
    //   95: getfield 53	com/instagram/explore/model/j:f	Ljava/lang/String;
    //   98: astore 5
    //   100: aload_3
    //   101: invokevirtual 97	com/a/a/a/k:d	()V
    //   104: aload_3
    //   105: ldc 99
    //   107: aload_0
    //   108: invokevirtual 102	com/a/a/a/k:a	(Ljava/lang/String;Ljava/lang/String;)V
    //   111: aload_3
    //   112: ldc 104
    //   114: aload 5
    //   116: invokevirtual 102	com/a/a/a/k:a	(Ljava/lang/String;Ljava/lang/String;)V
    //   119: aload_3
    //   120: invokevirtual 107	com/a/a/a/k:e	()V
    //   123: goto -93 -> 30
    //   126: astore_1
    //   127: aload_1
    //   128: athrow
    //   129: astore_0
    //   130: aload_3
    //   131: ifnull +11 -> 142
    //   134: aload_1
    //   135: ifnull +48 -> 183
    //   138: aload_3
    //   139: invokevirtual 59	com/a/a/a/k:close	()V
    //   142: aload_0
    //   143: athrow
    //   144: astore_0
    //   145: aload_2
    //   146: invokevirtual 63	java/io/StringWriter:toString	()Ljava/lang/String;
    //   149: areturn
    //   150: aload 5
    //   152: getfield 109	com/instagram/explore/model/RelatedItem:b	Ljava/lang/String;
    //   155: astore_0
    //   156: goto -66 -> 90
    //   159: aload_3
    //   160: invokevirtual 66	com/a/a/a/k:c	()V
    //   163: aload_3
    //   164: ifnull -19 -> 145
    //   167: aload_3
    //   168: invokevirtual 59	com/a/a/a/k:close	()V
    //   171: goto -26 -> 145
    //   174: astore_3
    //   175: aload_1
    //   176: aload_3
    //   177: invokestatic 71	com/facebook/a/a:a	(Ljava/lang/Throwable;Ljava/lang/Throwable;)V
    //   180: goto -38 -> 142
    //   183: aload_3
    //   184: invokevirtual 59	com/a/a/a/k:close	()V
    //   187: goto -45 -> 142
    //   190: astore_0
    //   191: goto -61 -> 130
    //   194: goto -110 -> 84
    // Local variable table:
    //   start	length	slot	name	signature
    //   0	197	0	paramList	java.util.List<com.instagram.explore.model.RelatedItem>
    //   17	1	1	localObject1	Object
    //   126	50	1	localThrowable1	Throwable
    //   7	139	2	localStringWriter	java.io.StringWriter
    //   15	153	3	localk	com.a.a.a.k
    //   174	10	3	localThrowable2	Throwable
    //   28	13	4	localIterator	java.util.Iterator
    //   50	101	5	localObject2	Object
    // Exception table:
    //   from	to	target	type
    //   18	30	126	java/lang/Throwable
    //   30	84	126	java/lang/Throwable
    //   84	90	126	java/lang/Throwable
    //   90	123	126	java/lang/Throwable
    //   150	156	126	java/lang/Throwable
    //   159	163	126	java/lang/Throwable
    //   127	129	129	finally
    //   8	16	144	java/io/IOException
    //   138	142	144	java/io/IOException
    //   142	144	144	java/io/IOException
    //   167	171	144	java/io/IOException
    //   175	180	144	java/io/IOException
    //   183	187	144	java/io/IOException
    //   138	142	174	java/lang/Throwable
    //   18	30	190	finally
    //   30	84	190	finally
    //   84	90	190	finally
    //   90	123	190	finally
    //   150	156	190	finally
    //   159	163	190	finally
  }
}

/* Location:
 * Qualified Name:     com.instagram.explore.b.j
 * Java Class Version: 6 (50.0)
 * JD-Core Version:    0.7.1
 */