package com.facebook.soloader;

final class r
  extends k
{
  final s[] a;
  
  /* Error */
  r(t paramt, m paramm)
  {
    // Byte code:
    //   0: aload_0
    //   1: aload_1
    //   2: putfield 14	com/facebook/soloader/r:b	Lcom/facebook/soloader/t;
    //   5: aload_0
    //   6: invokespecial 17	com/facebook/soloader/k:<init>	()V
    //   9: aload_1
    //   10: getfield 23	com/facebook/soloader/t:d	Landroid/content/Context;
    //   13: astore_1
    //   14: new 25	java/io/File
    //   17: dup
    //   18: new 27	java/lang/StringBuilder
    //   21: dup
    //   22: ldc 29
    //   24: invokespecial 32	java/lang/StringBuilder:<init>	(Ljava/lang/String;)V
    //   27: aload_1
    //   28: invokevirtual 38	android/content/Context:getPackageName	()Ljava/lang/String;
    //   31: invokevirtual 42	java/lang/StringBuilder:append	(Ljava/lang/String;)Ljava/lang/StringBuilder;
    //   34: ldc 44
    //   36: invokevirtual 42	java/lang/StringBuilder:append	(Ljava/lang/String;)Ljava/lang/StringBuilder;
    //   39: invokevirtual 47	java/lang/StringBuilder:toString	()Ljava/lang/String;
    //   42: invokespecial 48	java/io/File:<init>	(Ljava/lang/String;)V
    //   45: astore_1
    //   46: new 50	java/util/ArrayList
    //   49: dup
    //   50: invokespecial 51	java/util/ArrayList:<init>	()V
    //   53: astore 11
    //   55: new 53	java/util/LinkedHashSet
    //   58: dup
    //   59: invokespecial 54	java/util/LinkedHashSet:<init>	()V
    //   62: astore 12
    //   64: invokestatic 59	com/facebook/soloader/SysUtil:a	()[Ljava/lang/String;
    //   67: astore 13
    //   69: aload 13
    //   71: arraylength
    //   72: istore 5
    //   74: iconst_0
    //   75: istore_3
    //   76: iload_3
    //   77: iload 5
    //   79: if_icmpge +367 -> 446
    //   82: aload 13
    //   84: iload_3
    //   85: aaload
    //   86: astore 8
    //   88: new 25	java/io/File
    //   91: dup
    //   92: aload_1
    //   93: aload 8
    //   95: invokespecial 62	java/io/File:<init>	(Ljava/io/File;Ljava/lang/String;)V
    //   98: astore 14
    //   100: aload 14
    //   102: invokevirtual 66	java/io/File:isDirectory	()Z
    //   105: ifeq +296 -> 401
    //   108: aload 12
    //   110: aload 8
    //   112: invokeinterface 72 2 0
    //   117: pop
    //   118: new 25	java/io/File
    //   121: dup
    //   122: aload 14
    //   124: ldc 74
    //   126: invokespecial 62	java/io/File:<init>	(Ljava/io/File;Ljava/lang/String;)V
    //   129: astore 8
    //   131: aload 8
    //   133: invokevirtual 77	java/io/File:isFile	()Z
    //   136: ifeq +265 -> 401
    //   139: new 79	java/io/FileReader
    //   142: dup
    //   143: aload 8
    //   145: invokespecial 82	java/io/FileReader:<init>	(Ljava/io/File;)V
    //   148: astore 9
    //   150: new 84	java/io/BufferedReader
    //   153: dup
    //   154: aload 9
    //   156: invokespecial 87	java/io/BufferedReader:<init>	(Ljava/io/Reader;)V
    //   159: astore 10
    //   161: aconst_null
    //   162: astore 8
    //   164: aload 10
    //   166: invokevirtual 90	java/io/BufferedReader:readLine	()Ljava/lang/String;
    //   169: astore 16
    //   171: aload 16
    //   173: ifnull +218 -> 391
    //   176: aload 16
    //   178: invokevirtual 96	java/lang/String:length	()I
    //   181: ifeq -17 -> 164
    //   184: aload 16
    //   186: bipush 32
    //   188: invokevirtual 100	java/lang/String:indexOf	(I)I
    //   191: istore 6
    //   193: iload 6
    //   195: iconst_m1
    //   196: if_icmpne +63 -> 259
    //   199: new 102	java/lang/RuntimeException
    //   202: dup
    //   203: new 27	java/lang/StringBuilder
    //   206: dup
    //   207: ldc 104
    //   209: invokespecial 32	java/lang/StringBuilder:<init>	(Ljava/lang/String;)V
    //   212: aload 16
    //   214: invokevirtual 42	java/lang/StringBuilder:append	(Ljava/lang/String;)Ljava/lang/StringBuilder;
    //   217: ldc 106
    //   219: invokevirtual 42	java/lang/StringBuilder:append	(Ljava/lang/String;)Ljava/lang/StringBuilder;
    //   222: invokevirtual 47	java/lang/StringBuilder:toString	()Ljava/lang/String;
    //   225: invokespecial 107	java/lang/RuntimeException:<init>	(Ljava/lang/String;)V
    //   228: athrow
    //   229: astore_2
    //   230: aload_2
    //   231: athrow
    //   232: astore_1
    //   233: aload_2
    //   234: ifnull +185 -> 419
    //   237: aload 10
    //   239: invokevirtual 110	java/io/BufferedReader:close	()V
    //   242: aload_1
    //   243: athrow
    //   244: astore_2
    //   245: aload_2
    //   246: athrow
    //   247: astore_1
    //   248: aload_2
    //   249: ifnull +189 -> 438
    //   252: aload 9
    //   254: invokevirtual 111	java/io/FileReader:close	()V
    //   257: aload_1
    //   258: athrow
    //   259: new 27	java/lang/StringBuilder
    //   262: dup
    //   263: invokespecial 112	java/lang/StringBuilder:<init>	()V
    //   266: aload 16
    //   268: iconst_0
    //   269: iload 6
    //   271: invokevirtual 116	java/lang/String:substring	(II)Ljava/lang/String;
    //   274: invokevirtual 42	java/lang/StringBuilder:append	(Ljava/lang/String;)Ljava/lang/StringBuilder;
    //   277: ldc 118
    //   279: invokevirtual 42	java/lang/StringBuilder:append	(Ljava/lang/String;)Ljava/lang/StringBuilder;
    //   282: invokevirtual 47	java/lang/StringBuilder:toString	()Ljava/lang/String;
    //   285: astore 15
    //   287: aload 11
    //   289: invokevirtual 121	java/util/ArrayList:size	()I
    //   292: istore 7
    //   294: iconst_0
    //   295: istore 4
    //   297: iload 4
    //   299: iload 7
    //   301: if_icmpge +190 -> 491
    //   304: aload 11
    //   306: iload 4
    //   308: invokevirtual 125	java/util/ArrayList:get	(I)Ljava/lang/Object;
    //   311: checkcast 127	com/facebook/soloader/s
    //   314: getfield 131	com/facebook/soloader/s:c	Ljava/lang/String;
    //   317: aload 15
    //   319: invokevirtual 134	java/lang/String:equals	(Ljava/lang/Object;)Z
    //   322: ifeq +60 -> 382
    //   325: iconst_1
    //   326: istore 4
    //   328: iload 4
    //   330: ifne -166 -> 164
    //   333: aload 16
    //   335: iload 6
    //   337: iconst_1
    //   338: iadd
    //   339: invokevirtual 137	java/lang/String:substring	(I)Ljava/lang/String;
    //   342: astore 16
    //   344: aload 11
    //   346: new 127	com/facebook/soloader/s
    //   349: dup
    //   350: aload 15
    //   352: aload 16
    //   354: new 25	java/io/File
    //   357: dup
    //   358: aload 14
    //   360: aload 16
    //   362: invokespecial 62	java/io/File:<init>	(Ljava/io/File;Ljava/lang/String;)V
    //   365: invokespecial 140	com/facebook/soloader/s:<init>	(Ljava/lang/String;Ljava/lang/String;Ljava/io/File;)V
    //   368: invokevirtual 141	java/util/ArrayList:add	(Ljava/lang/Object;)Z
    //   371: pop
    //   372: goto -208 -> 164
    //   375: astore_1
    //   376: aload 8
    //   378: astore_2
    //   379: goto -146 -> 233
    //   382: iload 4
    //   384: iconst_1
    //   385: iadd
    //   386: istore 4
    //   388: goto -91 -> 297
    //   391: aload 10
    //   393: invokevirtual 110	java/io/BufferedReader:close	()V
    //   396: aload 9
    //   398: invokevirtual 111	java/io/FileReader:close	()V
    //   401: iload_3
    //   402: iconst_1
    //   403: iadd
    //   404: istore_3
    //   405: goto -329 -> 76
    //   408: astore 8
    //   410: aload_2
    //   411: aload 8
    //   413: invokestatic 146	com/facebook/a/a:a	(Ljava/lang/Throwable;Ljava/lang/Throwable;)V
    //   416: goto -174 -> 242
    //   419: aload 10
    //   421: invokevirtual 110	java/io/BufferedReader:close	()V
    //   424: goto -182 -> 242
    //   427: astore 8
    //   429: aload_2
    //   430: aload 8
    //   432: invokestatic 146	com/facebook/a/a:a	(Ljava/lang/Throwable;Ljava/lang/Throwable;)V
    //   435: goto -178 -> 257
    //   438: aload 9
    //   440: invokevirtual 111	java/io/FileReader:close	()V
    //   443: goto -186 -> 257
    //   446: aload_2
    //   447: aload 12
    //   449: aload 12
    //   451: invokeinterface 147 1 0
    //   456: anewarray 92	java/lang/String
    //   459: invokeinterface 151 2 0
    //   464: checkcast 153	[Ljava/lang/String;
    //   467: putfield 158	com/facebook/soloader/m:e	[Ljava/lang/String;
    //   470: aload_0
    //   471: aload 11
    //   473: aload 11
    //   475: invokevirtual 121	java/util/ArrayList:size	()I
    //   478: anewarray 127	com/facebook/soloader/s
    //   481: invokevirtual 159	java/util/ArrayList:toArray	([Ljava/lang/Object;)[Ljava/lang/Object;
    //   484: checkcast 160	[Lcom/facebook/soloader/s;
    //   487: putfield 162	com/facebook/soloader/r:a	[Lcom/facebook/soloader/s;
    //   490: return
    //   491: iconst_0
    //   492: istore 4
    //   494: goto -166 -> 328
    //   497: astore_1
    //   498: aconst_null
    //   499: astore_2
    //   500: goto -252 -> 248
    // Local variable table:
    //   start	length	slot	name	signature
    //   0	503	0	this	r
    //   0	503	1	paramt	t
    //   0	503	2	paramm	m
    //   75	330	3	i	int
    //   295	198	4	j	int
    //   72	8	5	k	int
    //   191	148	6	m	int
    //   292	10	7	n	int
    //   86	291	8	localObject	Object
    //   408	4	8	localThrowable1	Throwable
    //   427	4	8	localThrowable2	Throwable
    //   148	291	9	localFileReader	java.io.FileReader
    //   159	261	10	localBufferedReader	java.io.BufferedReader
    //   53	421	11	localArrayList	java.util.ArrayList
    //   62	388	12	localLinkedHashSet	java.util.LinkedHashSet
    //   67	16	13	arrayOfString	String[]
    //   98	261	14	localFile	java.io.File
    //   285	66	15	str1	String
    //   169	192	16	str2	String
    // Exception table:
    //   from	to	target	type
    //   164	171	229	java/lang/Throwable
    //   176	193	229	java/lang/Throwable
    //   199	229	229	java/lang/Throwable
    //   259	294	229	java/lang/Throwable
    //   304	325	229	java/lang/Throwable
    //   333	372	229	java/lang/Throwable
    //   230	232	232	finally
    //   150	161	244	java/lang/Throwable
    //   242	244	244	java/lang/Throwable
    //   391	396	244	java/lang/Throwable
    //   410	416	244	java/lang/Throwable
    //   419	424	244	java/lang/Throwable
    //   245	247	247	finally
    //   164	171	375	finally
    //   176	193	375	finally
    //   199	229	375	finally
    //   259	294	375	finally
    //   304	325	375	finally
    //   333	372	375	finally
    //   237	242	408	java/lang/Throwable
    //   252	257	427	java/lang/Throwable
    //   150	161	497	finally
    //   237	242	497	finally
    //   242	244	497	finally
    //   391	396	497	finally
    //   410	416	497	finally
    //   419	424	497	finally
  }
  
  protected final h b()
  {
    return new h(a);
  }
  
  protected final j c()
  {
    return new q(this, (byte)0);
  }
}

/* Location:
 * Qualified Name:     com.facebook.soloader.r
 * Java Class Version: 6 (50.0)
 * JD-Core Version:    0.7.1
 */