package com.facebook.rti.b.g;

final class f
  implements Runnable
{
  f(h paramh, String paramString, int paramInt1, boolean paramBoolean1, com.facebook.rti.b.g.b.f paramf, int paramInt2, boolean paramBoolean2) {}
  
  /* Error */
  public final void run()
  {
    // Byte code:
    //   0: aload_0
    //   1: getfield 22	com/facebook/rti/b/g/f:g	Lcom/facebook/rti/b/g/h;
    //   4: aload_0
    //   5: getfield 24	com/facebook/rti/b/g/f:a	Ljava/lang/String;
    //   8: aload_0
    //   9: getfield 26	com/facebook/rti/b/g/f:b	I
    //   12: aload_0
    //   13: getfield 28	com/facebook/rti/b/g/f:c	Z
    //   16: aload_0
    //   17: getfield 30	com/facebook/rti/b/g/f:d	Lcom/facebook/rti/b/g/b/f;
    //   20: aload_0
    //   21: getfield 32	com/facebook/rti/b/g/f:e	I
    //   24: aload_0
    //   25: getfield 34	com/facebook/rti/b/g/f:f	Z
    //   28: invokevirtual 52	com/facebook/rti/b/g/h:b	(Ljava/lang/String;IZLcom/facebook/rti/b/g/b/f;IZ)Lcom/facebook/rti/b/g/e;
    //   31: astore_2
    //   32: aload_2
    //   33: getfield 56	com/facebook/rti/b/g/e:a	Z
    //   36: ifne +72 -> 108
    //   39: aload_0
    //   40: getfield 22	com/facebook/rti/b/g/f:g	Lcom/facebook/rti/b/g/h;
    //   43: astore_1
    //   44: ldc 58
    //   46: ldc 60
    //   48: iconst_0
    //   49: anewarray 4	java/lang/Object
    //   52: invokestatic 65	com/facebook/rti/a/f/a:d	(Ljava/lang/String;Ljava/lang/String;[Ljava/lang/Object;)V
    //   55: aload_1
    //   56: getfield 68	com/facebook/rti/b/g/h:a	Ljava/net/Socket;
    //   59: astore_3
    //   60: aload_3
    //   61: ifnull +7 -> 68
    //   64: aload_3
    //   65: invokevirtual 73	java/net/Socket:close	()V
    //   68: aload_1
    //   69: monitorenter
    //   70: aload_1
    //   71: aconst_null
    //   72: putfield 68	com/facebook/rti/b/g/h:a	Ljava/net/Socket;
    //   75: aload_1
    //   76: aconst_null
    //   77: putfield 76	com/facebook/rti/b/g/h:b	Lcom/facebook/rti/b/g/c/c;
    //   80: aload_1
    //   81: aconst_null
    //   82: putfield 79	com/facebook/rti/b/g/h:c	Lcom/facebook/rti/b/g/c/e;
    //   85: aload_1
    //   86: getfield 82	com/facebook/rti/b/g/h:d	Lcom/facebook/rti/b/g/ab;
    //   89: getstatic 87	com/facebook/rti/b/g/d:d	Lcom/facebook/rti/b/g/d;
    //   92: invokeinterface 92 2 0
    //   97: aload_1
    //   98: monitorexit
    //   99: aload_1
    //   100: getfield 82	com/facebook/rti/b/g/h:d	Lcom/facebook/rti/b/g/ab;
    //   103: invokeinterface 94 1 0
    //   108: aload_0
    //   109: getfield 22	com/facebook/rti/b/g/f:g	Lcom/facebook/rti/b/g/h;
    //   112: getfield 82	com/facebook/rti/b/g/h:d	Lcom/facebook/rti/b/g/ab;
    //   115: aload_2
    //   116: invokeinterface 97 2 0
    //   121: aload_0
    //   122: getfield 22	com/facebook/rti/b/g/f:g	Lcom/facebook/rti/b/g/h;
    //   125: astore_1
    //   126: aload_1
    //   127: monitorenter
    //   128: aload_1
    //   129: getfield 82	com/facebook/rti/b/g/h:d	Lcom/facebook/rti/b/g/ab;
    //   132: getstatic 99	com/facebook/rti/b/g/d:c	Lcom/facebook/rti/b/g/d;
    //   135: invokeinterface 102 2 0
    //   140: ifne +106 -> 246
    //   143: aload_1
    //   144: monitorexit
    //   145: aload_1
    //   146: getfield 82	com/facebook/rti/b/g/h:d	Lcom/facebook/rti/b/g/ab;
    //   149: getstatic 87	com/facebook/rti/b/g/d:d	Lcom/facebook/rti/b/g/d;
    //   152: invokeinterface 92 2 0
    //   157: aload_1
    //   158: getfield 82	com/facebook/rti/b/g/h:d	Lcom/facebook/rti/b/g/ab;
    //   161: invokeinterface 94 1 0
    //   166: ldc 58
    //   168: ldc 104
    //   170: iconst_0
    //   171: anewarray 4	java/lang/Object
    //   174: invokestatic 65	com/facebook/rti/a/f/a:d	(Ljava/lang/String;Ljava/lang/String;[Ljava/lang/Object;)V
    //   177: return
    //   178: astore_2
    //   179: aload_1
    //   180: monitorexit
    //   181: aload_2
    //   182: athrow
    //   183: astore_1
    //   184: ldc 58
    //   186: aload_1
    //   187: ldc 106
    //   189: iconst_0
    //   190: anewarray 4	java/lang/Object
    //   193: invokestatic 109	com/facebook/rti/a/f/a:b	(Ljava/lang/String;Ljava/lang/Throwable;Ljava/lang/String;[Ljava/lang/Object;)V
    //   196: aload_0
    //   197: getfield 22	com/facebook/rti/b/g/f:g	Lcom/facebook/rti/b/g/h;
    //   200: getfield 82	com/facebook/rti/b/g/h:d	Lcom/facebook/rti/b/g/ab;
    //   203: aload_1
    //   204: invokeinterface 112 2 0
    //   209: aload_0
    //   210: getfield 22	com/facebook/rti/b/g/f:g	Lcom/facebook/rti/b/g/h;
    //   213: getfield 82	com/facebook/rti/b/g/h:d	Lcom/facebook/rti/b/g/ab;
    //   216: getstatic 118	com/facebook/rti/b/b/a/b:v	Lcom/facebook/rti/b/b/a/b;
    //   219: getstatic 123	com/facebook/rti/b/g/ah:b	Lcom/facebook/rti/b/g/ah;
    //   222: aload_1
    //   223: invokeinterface 126 4 0
    //   228: aload_0
    //   229: getfield 22	com/facebook/rti/b/g/f:g	Lcom/facebook/rti/b/g/h;
    //   232: getfield 82	com/facebook/rti/b/g/h:d	Lcom/facebook/rti/b/g/ab;
    //   235: aload_1
    //   236: ldc -128
    //   238: ldc -126
    //   240: invokeinterface 133 4 0
    //   245: return
    //   246: aload_1
    //   247: getfield 76	com/facebook/rti/b/g/h:b	Lcom/facebook/rti/b/g/c/c;
    //   250: astore_2
    //   251: aload_1
    //   252: monitorexit
    //   253: aload_2
    //   254: invokevirtual 138	com/facebook/rti/b/g/c/c:a	()Lcom/facebook/rti/b/g/b/m;
    //   257: astore_2
    //   258: aload_1
    //   259: getfield 82	com/facebook/rti/b/g/h:d	Lcom/facebook/rti/b/g/ab;
    //   262: aload_2
    //   263: invokeinterface 141 2 0
    //   268: goto -142 -> 126
    //   271: astore_2
    //   272: aload_1
    //   273: monitorexit
    //   274: aload_2
    //   275: athrow
    //   276: astore_2
    //   277: aload_1
    //   278: getfield 82	com/facebook/rti/b/g/h:d	Lcom/facebook/rti/b/g/ab;
    //   281: aload_2
    //   282: invokestatic 144	com/facebook/rti/b/b/a/b:a	(Ljava/lang/Throwable;)Lcom/facebook/rti/b/b/a/b;
    //   285: getstatic 123	com/facebook/rti/b/g/ah:b	Lcom/facebook/rti/b/g/ah;
    //   288: aload_2
    //   289: invokeinterface 126 4 0
    //   294: goto -149 -> 145
    //   297: astore_2
    //   298: aload_1
    //   299: getfield 82	com/facebook/rti/b/g/h:d	Lcom/facebook/rti/b/g/ab;
    //   302: aload_2
    //   303: invokestatic 144	com/facebook/rti/b/b/a/b:a	(Ljava/lang/Throwable;)Lcom/facebook/rti/b/b/a/b;
    //   306: getstatic 123	com/facebook/rti/b/g/ah:b	Lcom/facebook/rti/b/g/ah;
    //   309: aload_2
    //   310: invokeinterface 126 4 0
    //   315: goto -170 -> 145
    //   318: astore_2
    //   319: aload_1
    //   320: getfield 82	com/facebook/rti/b/g/h:d	Lcom/facebook/rti/b/g/ab;
    //   323: aload_2
    //   324: invokestatic 144	com/facebook/rti/b/b/a/b:a	(Ljava/lang/Throwable;)Lcom/facebook/rti/b/b/a/b;
    //   327: getstatic 123	com/facebook/rti/b/g/ah:b	Lcom/facebook/rti/b/g/ah;
    //   330: aload_2
    //   331: invokeinterface 126 4 0
    //   336: goto -191 -> 145
    //   339: astore_3
    //   340: goto -272 -> 68
    // Local variable table:
    //   start	length	slot	name	signature
    //   0	343	0	this	f
    //   183	137	1	localThrowable	Throwable
    //   31	85	2	locale	e
    //   178	4	2	localObject1	Object
    //   250	13	2	localObject2	Object
    //   271	4	2	localObject3	Object
    //   276	13	2	localIOException1	java.io.IOException
    //   297	13	2	localDataFormatException	java.util.zip.DataFormatException
    //   318	13	2	localJSONException	org.json.JSONException
    //   59	6	3	localSocket	java.net.Socket
    //   339	1	3	localIOException2	java.io.IOException
    // Exception table:
    //   from	to	target	type
    //   70	99	178	finally
    //   179	181	178	finally
    //   0	60	183	java/lang/Throwable
    //   64	68	183	java/lang/Throwable
    //   68	70	183	java/lang/Throwable
    //   99	108	183	java/lang/Throwable
    //   108	126	183	java/lang/Throwable
    //   126	128	183	java/lang/Throwable
    //   145	177	183	java/lang/Throwable
    //   181	183	183	java/lang/Throwable
    //   253	258	183	java/lang/Throwable
    //   258	268	183	java/lang/Throwable
    //   274	276	183	java/lang/Throwable
    //   277	294	183	java/lang/Throwable
    //   298	315	183	java/lang/Throwable
    //   319	336	183	java/lang/Throwable
    //   128	145	271	finally
    //   246	253	271	finally
    //   272	274	271	finally
    //   253	258	276	java/io/IOException
    //   253	258	297	java/util/zip/DataFormatException
    //   253	258	318	org/json/JSONException
    //   64	68	339	java/io/IOException
  }
}

/* Location:
 * Qualified Name:     com.facebook.rti.b.g.f
 * Java Class Version: 6 (50.0)
 * JD-Core Version:    0.7.1
 */