package com.b.a;

public final class f
  implements Runnable
{
  public f(q paramq) {}
  
  /* Error */
  public final void run()
  {
    // Byte code:
    //   0: aload_0
    //   1: getfield 12	com/b/a/f:a	Lcom/b/a/q;
    //   4: getfield 29	com/b/a/q:h	Ljava/lang/Object;
    //   7: astore 4
    //   9: aload 4
    //   11: monitorenter
    //   12: bipush 16
    //   14: newarray <illegal type>
    //   16: astore_2
    //   17: iconst_0
    //   18: istore_1
    //   19: iload_1
    //   20: bipush 16
    //   22: if_icmpge +22 -> 44
    //   25: aload_2
    //   26: iload_1
    //   27: invokestatic 35	java/lang/Math:random	()D
    //   30: ldc2_w 36
    //   33: dmul
    //   34: d2i
    //   35: i2b
    //   36: bastore
    //   37: iload_1
    //   38: iconst_1
    //   39: iadd
    //   40: istore_1
    //   41: goto -22 -> 19
    //   44: aload_2
    //   45: iconst_0
    //   46: invokestatic 43	android/util/Base64:encodeToString	([BI)Ljava/lang/String;
    //   49: invokevirtual 49	java/lang/String:trim	()Ljava/lang/String;
    //   52: astore 5
    //   54: aload_0
    //   55: getfield 12	com/b/a/f:a	Lcom/b/a/q;
    //   58: getfield 52	com/b/a/q:a	Ljava/net/URI;
    //   61: invokevirtual 58	java/net/URI:getPort	()I
    //   64: iconst_m1
    //   65: if_icmpeq +477 -> 542
    //   68: aload_0
    //   69: getfield 12	com/b/a/f:a	Lcom/b/a/q;
    //   72: getfield 52	com/b/a/q:a	Ljava/net/URI;
    //   75: invokevirtual 58	java/net/URI:getPort	()I
    //   78: istore_1
    //   79: aload_0
    //   80: getfield 12	com/b/a/f:a	Lcom/b/a/q;
    //   83: getfield 52	com/b/a/q:a	Ljava/net/URI;
    //   86: invokevirtual 61	java/net/URI:getPath	()Ljava/lang/String;
    //   89: invokestatic 67	android/text/TextUtils:isEmpty	(Ljava/lang/CharSequence;)Z
    //   92: ifeq +475 -> 567
    //   95: ldc 69
    //   97: astore_2
    //   98: aload_0
    //   99: getfield 12	com/b/a/f:a	Lcom/b/a/q;
    //   102: getfield 52	com/b/a/q:a	Ljava/net/URI;
    //   105: invokevirtual 72	java/net/URI:getQuery	()Ljava/lang/String;
    //   108: invokestatic 67	android/text/TextUtils:isEmpty	(Ljava/lang/CharSequence;)Z
    //   111: ifne +733 -> 844
    //   114: new 74	java/lang/StringBuilder
    //   117: dup
    //   118: invokespecial 75	java/lang/StringBuilder:<init>	()V
    //   121: aload_2
    //   122: invokevirtual 79	java/lang/StringBuilder:append	(Ljava/lang/String;)Ljava/lang/StringBuilder;
    //   125: ldc 81
    //   127: invokevirtual 79	java/lang/StringBuilder:append	(Ljava/lang/String;)Ljava/lang/StringBuilder;
    //   130: aload_0
    //   131: getfield 12	com/b/a/f:a	Lcom/b/a/q;
    //   134: getfield 52	com/b/a/q:a	Ljava/net/URI;
    //   137: invokevirtual 72	java/net/URI:getQuery	()Ljava/lang/String;
    //   140: invokevirtual 79	java/lang/StringBuilder:append	(Ljava/lang/String;)Ljava/lang/StringBuilder;
    //   143: invokevirtual 84	java/lang/StringBuilder:toString	()Ljava/lang/String;
    //   146: astore_2
    //   147: aload_0
    //   148: getfield 12	com/b/a/f:a	Lcom/b/a/q;
    //   151: getfield 52	com/b/a/q:a	Ljava/net/URI;
    //   154: invokevirtual 87	java/net/URI:getScheme	()Ljava/lang/String;
    //   157: ldc 89
    //   159: invokevirtual 93	java/lang/String:equals	(Ljava/lang/Object;)Z
    //   162: ifeq +691 -> 853
    //   165: ldc 95
    //   167: astore_3
    //   168: new 54	java/net/URI
    //   171: dup
    //   172: aload_3
    //   173: new 74	java/lang/StringBuilder
    //   176: dup
    //   177: ldc 97
    //   179: invokespecial 100	java/lang/StringBuilder:<init>	(Ljava/lang/String;)V
    //   182: aload_0
    //   183: getfield 12	com/b/a/f:a	Lcom/b/a/q;
    //   186: getfield 52	com/b/a/q:a	Ljava/net/URI;
    //   189: invokevirtual 103	java/net/URI:getHost	()Ljava/lang/String;
    //   192: invokevirtual 79	java/lang/StringBuilder:append	(Ljava/lang/String;)Ljava/lang/StringBuilder;
    //   195: invokevirtual 84	java/lang/StringBuilder:toString	()Ljava/lang/String;
    //   198: aconst_null
    //   199: invokespecial 106	java/net/URI:<init>	(Ljava/lang/String;Ljava/lang/String;Ljava/lang/String;)V
    //   202: astore 6
    //   204: aload_0
    //   205: getfield 12	com/b/a/f:a	Lcom/b/a/q;
    //   208: aload_0
    //   209: getfield 12	com/b/a/f:a	Lcom/b/a/q;
    //   212: getfield 110	com/b/a/q:i	Lcom/b/a/b;
    //   215: aload_0
    //   216: getfield 12	com/b/a/f:a	Lcom/b/a/q;
    //   219: getfield 52	com/b/a/q:a	Ljava/net/URI;
    //   222: invokevirtual 87	java/net/URI:getScheme	()Ljava/lang/String;
    //   225: ldc 89
    //   227: invokevirtual 93	java/lang/String:equals	(Ljava/lang/Object;)Z
    //   230: invokeinterface 116 2 0
    //   235: putfield 120	com/b/a/q:c	Ljava/net/Socket;
    //   238: aload_0
    //   239: getfield 12	com/b/a/f:a	Lcom/b/a/q;
    //   242: getfield 110	com/b/a/q:i	Lcom/b/a/b;
    //   245: aload_0
    //   246: getfield 12	com/b/a/f:a	Lcom/b/a/q;
    //   249: getfield 120	com/b/a/q:c	Ljava/net/Socket;
    //   252: aload_0
    //   253: getfield 12	com/b/a/f:a	Lcom/b/a/q;
    //   256: getfield 52	com/b/a/q:a	Ljava/net/URI;
    //   259: invokevirtual 103	java/net/URI:getHost	()Ljava/lang/String;
    //   262: iload_1
    //   263: invokeinterface 124 4 0
    //   268: new 126	java/io/PrintWriter
    //   271: dup
    //   272: aload_0
    //   273: getfield 12	com/b/a/f:a	Lcom/b/a/q;
    //   276: getfield 120	com/b/a/q:c	Ljava/net/Socket;
    //   279: invokevirtual 132	java/net/Socket:getOutputStream	()Ljava/io/OutputStream;
    //   282: invokespecial 135	java/io/PrintWriter:<init>	(Ljava/io/OutputStream;)V
    //   285: astore_3
    //   286: aload_3
    //   287: new 74	java/lang/StringBuilder
    //   290: dup
    //   291: ldc -119
    //   293: invokespecial 100	java/lang/StringBuilder:<init>	(Ljava/lang/String;)V
    //   296: aload_2
    //   297: invokevirtual 79	java/lang/StringBuilder:append	(Ljava/lang/String;)Ljava/lang/StringBuilder;
    //   300: ldc -117
    //   302: invokevirtual 79	java/lang/StringBuilder:append	(Ljava/lang/String;)Ljava/lang/StringBuilder;
    //   305: invokevirtual 84	java/lang/StringBuilder:toString	()Ljava/lang/String;
    //   308: invokevirtual 142	java/io/PrintWriter:print	(Ljava/lang/String;)V
    //   311: aload_3
    //   312: ldc -112
    //   314: invokevirtual 142	java/io/PrintWriter:print	(Ljava/lang/String;)V
    //   317: aload_3
    //   318: ldc -110
    //   320: invokevirtual 142	java/io/PrintWriter:print	(Ljava/lang/String;)V
    //   323: aload_3
    //   324: new 74	java/lang/StringBuilder
    //   327: dup
    //   328: ldc -108
    //   330: invokespecial 100	java/lang/StringBuilder:<init>	(Ljava/lang/String;)V
    //   333: aload_0
    //   334: getfield 12	com/b/a/f:a	Lcom/b/a/q;
    //   337: getfield 52	com/b/a/q:a	Ljava/net/URI;
    //   340: invokevirtual 103	java/net/URI:getHost	()Ljava/lang/String;
    //   343: invokevirtual 79	java/lang/StringBuilder:append	(Ljava/lang/String;)Ljava/lang/StringBuilder;
    //   346: ldc -106
    //   348: invokevirtual 79	java/lang/StringBuilder:append	(Ljava/lang/String;)Ljava/lang/StringBuilder;
    //   351: invokevirtual 84	java/lang/StringBuilder:toString	()Ljava/lang/String;
    //   354: invokevirtual 142	java/io/PrintWriter:print	(Ljava/lang/String;)V
    //   357: aload_3
    //   358: new 74	java/lang/StringBuilder
    //   361: dup
    //   362: ldc -104
    //   364: invokespecial 100	java/lang/StringBuilder:<init>	(Ljava/lang/String;)V
    //   367: aload 6
    //   369: invokevirtual 153	java/net/URI:toString	()Ljava/lang/String;
    //   372: invokevirtual 79	java/lang/StringBuilder:append	(Ljava/lang/String;)Ljava/lang/StringBuilder;
    //   375: ldc -106
    //   377: invokevirtual 79	java/lang/StringBuilder:append	(Ljava/lang/String;)Ljava/lang/StringBuilder;
    //   380: invokevirtual 84	java/lang/StringBuilder:toString	()Ljava/lang/String;
    //   383: invokevirtual 142	java/io/PrintWriter:print	(Ljava/lang/String;)V
    //   386: aload_3
    //   387: new 74	java/lang/StringBuilder
    //   390: dup
    //   391: ldc -101
    //   393: invokespecial 100	java/lang/StringBuilder:<init>	(Ljava/lang/String;)V
    //   396: aload 5
    //   398: invokevirtual 79	java/lang/StringBuilder:append	(Ljava/lang/String;)Ljava/lang/StringBuilder;
    //   401: ldc -106
    //   403: invokevirtual 79	java/lang/StringBuilder:append	(Ljava/lang/String;)Ljava/lang/StringBuilder;
    //   406: invokevirtual 84	java/lang/StringBuilder:toString	()Ljava/lang/String;
    //   409: invokevirtual 142	java/io/PrintWriter:print	(Ljava/lang/String;)V
    //   412: aload_3
    //   413: ldc -99
    //   415: invokevirtual 142	java/io/PrintWriter:print	(Ljava/lang/String;)V
    //   418: aload_0
    //   419: getfield 12	com/b/a/f:a	Lcom/b/a/q;
    //   422: getfield 161	com/b/a/q:f	Ljava/util/List;
    //   425: ifnull +156 -> 581
    //   428: aload_0
    //   429: getfield 12	com/b/a/f:a	Lcom/b/a/q;
    //   432: getfield 161	com/b/a/q:f	Ljava/util/List;
    //   435: invokeinterface 167 1 0
    //   440: astore_2
    //   441: aload_2
    //   442: invokeinterface 173 1 0
    //   447: ifeq +134 -> 581
    //   450: aload_2
    //   451: invokeinterface 177 1 0
    //   456: checkcast 179	org/apache/http/NameValuePair
    //   459: astore 6
    //   461: aload_3
    //   462: ldc -75
    //   464: iconst_2
    //   465: anewarray 4	java/lang/Object
    //   468: dup
    //   469: iconst_0
    //   470: aload 6
    //   472: invokeinterface 184 1 0
    //   477: aastore
    //   478: dup
    //   479: iconst_1
    //   480: aload 6
    //   482: invokeinterface 187 1 0
    //   487: aastore
    //   488: invokestatic 191	java/lang/String:format	(Ljava/lang/String;[Ljava/lang/Object;)Ljava/lang/String;
    //   491: invokevirtual 142	java/io/PrintWriter:print	(Ljava/lang/String;)V
    //   494: goto -53 -> 441
    //   497: astore_2
    //   498: aload 4
    //   500: monitorexit
    //   501: aload_2
    //   502: athrow
    //   503: astore_2
    //   504: aload_0
    //   505: getfield 12	com/b/a/f:a	Lcom/b/a/q;
    //   508: getfield 29	com/b/a/q:h	Ljava/lang/Object;
    //   511: astore_2
    //   512: aload_2
    //   513: monitorenter
    //   514: aload_0
    //   515: getfield 12	com/b/a/f:a	Lcom/b/a/q;
    //   518: getfield 120	com/b/a/q:c	Ljava/net/Socket;
    //   521: ifnull +289 -> 810
    //   524: aload_0
    //   525: getfield 12	com/b/a/f:a	Lcom/b/a/q;
    //   528: getfield 195	com/b/a/q:b	Lcom/b/a/p;
    //   531: sipush 64336
    //   534: ldc -59
    //   536: invokevirtual 203	com/b/a/p:onDisconnect	(ILjava/lang/String;)V
    //   539: aload_2
    //   540: monitorexit
    //   541: return
    //   542: aload_0
    //   543: getfield 12	com/b/a/f:a	Lcom/b/a/q;
    //   546: getfield 52	com/b/a/q:a	Ljava/net/URI;
    //   549: invokevirtual 87	java/net/URI:getScheme	()Ljava/lang/String;
    //   552: ldc 89
    //   554: invokevirtual 93	java/lang/String:equals	(Ljava/lang/Object;)Z
    //   557: ifeq +290 -> 847
    //   560: sipush 443
    //   563: istore_1
    //   564: goto -485 -> 79
    //   567: aload_0
    //   568: getfield 12	com/b/a/f:a	Lcom/b/a/q;
    //   571: getfield 52	com/b/a/q:a	Ljava/net/URI;
    //   574: invokevirtual 61	java/net/URI:getPath	()Ljava/lang/String;
    //   577: astore_2
    //   578: goto -480 -> 98
    //   581: aload_3
    //   582: ldc -106
    //   584: invokevirtual 142	java/io/PrintWriter:print	(Ljava/lang/String;)V
    //   587: aload_3
    //   588: invokevirtual 206	java/io/PrintWriter:flush	()V
    //   591: new 208	com/b/a/d
    //   594: dup
    //   595: aload_0
    //   596: getfield 12	com/b/a/f:a	Lcom/b/a/q;
    //   599: getfield 120	com/b/a/q:c	Ljava/net/Socket;
    //   602: invokevirtual 212	java/net/Socket:getInputStream	()Ljava/io/InputStream;
    //   605: invokespecial 215	com/b/a/d:<init>	(Ljava/io/InputStream;)V
    //   608: astore_3
    //   609: aload_3
    //   610: invokestatic 218	com/b/a/q:a	(Lcom/b/a/d;)Ljava/lang/String;
    //   613: astore_2
    //   614: aload_2
    //   615: invokestatic 67	android/text/TextUtils:isEmpty	(Ljava/lang/CharSequence;)Z
    //   618: ifeq +19 -> 637
    //   621: aconst_null
    //   622: astore_2
    //   623: aload_2
    //   624: ifnonnull +28 -> 652
    //   627: new 220	org/apache/http/HttpException
    //   630: dup
    //   631: ldc -34
    //   633: invokespecial 223	org/apache/http/HttpException:<init>	(Ljava/lang/String;)V
    //   636: athrow
    //   637: aload_2
    //   638: new 225	org/apache/http/message/BasicLineParser
    //   641: dup
    //   642: invokespecial 226	org/apache/http/message/BasicLineParser:<init>	()V
    //   645: invokestatic 230	org/apache/http/message/BasicLineParser:parseStatusLine	(Ljava/lang/String;Lorg/apache/http/message/LineParser;)Lorg/apache/http/StatusLine;
    //   648: astore_2
    //   649: goto -26 -> 623
    //   652: aload_2
    //   653: invokeinterface 235 1 0
    //   658: bipush 101
    //   660: if_icmpeq +200 -> 860
    //   663: new 237	org/apache/http/client/HttpResponseException
    //   666: dup
    //   667: aload_2
    //   668: invokeinterface 235 1 0
    //   673: aload_2
    //   674: invokeinterface 240 1 0
    //   679: invokespecial 242	org/apache/http/client/HttpResponseException:<init>	(ILjava/lang/String;)V
    //   682: athrow
    //   683: aload_3
    //   684: invokestatic 218	com/b/a/q:a	(Lcom/b/a/d;)Ljava/lang/String;
    //   687: astore_2
    //   688: aload_2
    //   689: invokestatic 67	android/text/TextUtils:isEmpty	(Ljava/lang/CharSequence;)Z
    //   692: ifne +60 -> 752
    //   695: aload_2
    //   696: new 225	org/apache/http/message/BasicLineParser
    //   699: dup
    //   700: invokespecial 226	org/apache/http/message/BasicLineParser:<init>	()V
    //   703: invokestatic 246	org/apache/http/message/BasicLineParser:parseHeader	(Ljava/lang/String;Lorg/apache/http/message/LineParser;)Lorg/apache/http/Header;
    //   706: astore_2
    //   707: aload_2
    //   708: invokeinterface 249 1 0
    //   713: ldc -5
    //   715: invokevirtual 93	java/lang/String:equals	(Ljava/lang/Object;)Z
    //   718: ifeq -35 -> 683
    //   721: aload 5
    //   723: invokestatic 254	com/b/a/q:b	(Ljava/lang/String;)Ljava/lang/String;
    //   726: aload_2
    //   727: invokeinterface 255 1 0
    //   732: invokevirtual 49	java/lang/String:trim	()Ljava/lang/String;
    //   735: invokevirtual 93	java/lang/String:equals	(Ljava/lang/Object;)Z
    //   738: ifne +127 -> 865
    //   741: new 220	org/apache/http/HttpException
    //   744: dup
    //   745: ldc_w 257
    //   748: invokespecial 223	org/apache/http/HttpException:<init>	(Ljava/lang/String;)V
    //   751: athrow
    //   752: iload_1
    //   753: ifne +14 -> 767
    //   756: new 220	org/apache/http/HttpException
    //   759: dup
    //   760: ldc_w 259
    //   763: invokespecial 223	org/apache/http/HttpException:<init>	(Ljava/lang/String;)V
    //   766: athrow
    //   767: aload_0
    //   768: getfield 12	com/b/a/f:a	Lcom/b/a/q;
    //   771: getfield 195	com/b/a/q:b	Lcom/b/a/p;
    //   774: invokevirtual 262	com/b/a/p:onConnect	()V
    //   777: aload 4
    //   779: monitorexit
    //   780: aload_0
    //   781: getfield 12	com/b/a/f:a	Lcom/b/a/q;
    //   784: getfield 266	com/b/a/q:g	Lcom/b/a/e;
    //   787: aload_3
    //   788: invokevirtual 271	com/b/a/e:a	(Lcom/b/a/d;)V
    //   791: return
    //   792: astore_2
    //   793: aload_0
    //   794: getfield 12	com/b/a/f:a	Lcom/b/a/q;
    //   797: getfield 195	com/b/a/q:b	Lcom/b/a/p;
    //   800: sipush 64436
    //   803: ldc_w 273
    //   806: invokevirtual 203	com/b/a/p:onDisconnect	(ILjava/lang/String;)V
    //   809: return
    //   810: aload_0
    //   811: getfield 12	com/b/a/f:a	Lcom/b/a/q;
    //   814: getfield 195	com/b/a/q:b	Lcom/b/a/p;
    //   817: iconst_0
    //   818: ldc -59
    //   820: invokevirtual 203	com/b/a/p:onDisconnect	(ILjava/lang/String;)V
    //   823: goto -284 -> 539
    //   826: astore_3
    //   827: aload_2
    //   828: monitorexit
    //   829: aload_3
    //   830: athrow
    //   831: astore_2
    //   832: aload_0
    //   833: getfield 12	com/b/a/f:a	Lcom/b/a/q;
    //   836: getfield 195	com/b/a/q:b	Lcom/b/a/p;
    //   839: aload_2
    //   840: invokevirtual 277	com/b/a/p:onError	(Ljava/lang/Exception;)V
    //   843: return
    //   844: goto -697 -> 147
    //   847: bipush 80
    //   849: istore_1
    //   850: goto -771 -> 79
    //   853: ldc_w 279
    //   856: astore_3
    //   857: goto -689 -> 168
    //   860: iconst_0
    //   861: istore_1
    //   862: goto -179 -> 683
    //   865: iconst_1
    //   866: istore_1
    //   867: goto -184 -> 683
    // Local variable table:
    //   start	length	slot	name	signature
    //   0	870	0	this	f
    //   18	849	1	i	int
    //   16	435	2	localObject1	Object
    //   497	5	2	localObject2	Object
    //   503	1	2	localEOFException	java.io.EOFException
    //   792	36	2	localSSLException	javax.net.ssl.SSLException
    //   831	9	2	localException	Exception
    //   167	621	3	localObject4	Object
    //   826	4	3	localObject5	Object
    //   856	1	3	str1	String
    //   52	670	5	str2	String
    //   202	279	6	localObject7	Object
    // Exception table:
    //   from	to	target	type
    //   12	17	497	finally
    //   25	37	497	finally
    //   44	79	497	finally
    //   79	95	497	finally
    //   98	147	497	finally
    //   147	165	497	finally
    //   168	441	497	finally
    //   441	494	497	finally
    //   498	501	497	finally
    //   542	560	497	finally
    //   567	578	497	finally
    //   581	621	497	finally
    //   627	637	497	finally
    //   637	649	497	finally
    //   652	683	497	finally
    //   683	752	497	finally
    //   756	767	497	finally
    //   767	780	497	finally
    //   0	12	503	java/io/EOFException
    //   501	503	503	java/io/EOFException
    //   780	791	503	java/io/EOFException
    //   0	12	792	javax/net/ssl/SSLException
    //   501	503	792	javax/net/ssl/SSLException
    //   780	791	792	javax/net/ssl/SSLException
    //   514	539	826	finally
    //   539	541	826	finally
    //   810	823	826	finally
    //   827	829	826	finally
    //   0	12	831	java/lang/Exception
    //   501	503	831	java/lang/Exception
    //   780	791	831	java/lang/Exception
  }
}

/* Location:
 * Qualified Name:     com.b.a.f
 * Java Class Version: 6 (50.0)
 * JD-Core Version:    0.7.1
 */