package com.b.a;

final class g
  implements Runnable
{
  g(q paramq) {}
  
  /* Error */
  public final void run()
  {
    // Byte code:
    //   0: aload_0
    //   1: getfield 12	com/b/a/g:a	Lcom/b/a/q;
    //   4: getfield 27	com/b/a/q:h	Ljava/lang/Object;
    //   7: astore_1
    //   8: aload_1
    //   9: monitorenter
    //   10: aload_0
    //   11: getfield 12	com/b/a/g:a	Lcom/b/a/q;
    //   14: getfield 31	com/b/a/q:c	Ljava/net/Socket;
    //   17: astore_2
    //   18: aload_2
    //   19: ifnull +41 -> 60
    //   22: aload_0
    //   23: getfield 12	com/b/a/g:a	Lcom/b/a/q;
    //   26: getfield 31	com/b/a/q:c	Ljava/net/Socket;
    //   29: invokevirtual 36	java/net/Socket:shutdownOutput	()V
    //   32: aload_0
    //   33: getfield 12	com/b/a/g:a	Lcom/b/a/q;
    //   36: getfield 31	com/b/a/q:c	Ljava/net/Socket;
    //   39: invokevirtual 39	java/net/Socket:shutdownInput	()V
    //   42: aload_0
    //   43: getfield 12	com/b/a/g:a	Lcom/b/a/q;
    //   46: getfield 31	com/b/a/q:c	Ljava/net/Socket;
    //   49: invokevirtual 42	java/net/Socket:close	()V
    //   52: aload_0
    //   53: getfield 12	com/b/a/g:a	Lcom/b/a/q;
    //   56: aconst_null
    //   57: putfield 31	com/b/a/q:c	Ljava/net/Socket;
    //   60: aload_1
    //   61: monitorexit
    //   62: aload_0
    //   63: getfield 12	com/b/a/g:a	Lcom/b/a/q;
    //   66: getfield 46	com/b/a/q:e	Landroid/os/HandlerThread;
    //   69: invokevirtual 52	android/os/HandlerThread:quit	()Z
    //   72: pop
    //   73: return
    //   74: astore_2
    //   75: aload_0
    //   76: getfield 12	com/b/a/g:a	Lcom/b/a/q;
    //   79: getfield 31	com/b/a/q:c	Ljava/net/Socket;
    //   82: invokevirtual 42	java/net/Socket:close	()V
    //   85: aload_0
    //   86: getfield 12	com/b/a/g:a	Lcom/b/a/q;
    //   89: aconst_null
    //   90: putfield 31	com/b/a/q:c	Ljava/net/Socket;
    //   93: aload_2
    //   94: athrow
    //   95: astore_2
    //   96: aload_1
    //   97: monitorexit
    //   98: aload_2
    //   99: athrow
    //   100: astore_1
    //   101: aload_0
    //   102: getfield 12	com/b/a/g:a	Lcom/b/a/q;
    //   105: getfield 56	com/b/a/q:b	Lcom/b/a/p;
    //   108: aload_1
    //   109: invokevirtual 62	com/b/a/p:onError	(Ljava/lang/Exception;)V
    //   112: aload_0
    //   113: getfield 12	com/b/a/g:a	Lcom/b/a/q;
    //   116: getfield 46	com/b/a/q:e	Landroid/os/HandlerThread;
    //   119: invokevirtual 52	android/os/HandlerThread:quit	()Z
    //   122: pop
    //   123: return
    //   124: astore_1
    //   125: aload_0
    //   126: getfield 12	com/b/a/g:a	Lcom/b/a/q;
    //   129: getfield 46	com/b/a/q:e	Landroid/os/HandlerThread;
    //   132: invokevirtual 52	android/os/HandlerThread:quit	()Z
    //   135: pop
    //   136: aload_1
    //   137: athrow
    //   138: astore_2
    //   139: goto -97 -> 42
    //   142: astore_2
    //   143: goto -101 -> 42
    //   146: astore_2
    //   147: goto -115 -> 32
    // Local variable table:
    //   start	length	slot	name	signature
    //   0	150	0	this	g
    //   7	90	1	localObject1	Object
    //   100	9	1	localIOException1	java.io.IOException
    //   124	13	1	localObject2	Object
    //   17	2	2	localSocket	java.net.Socket
    //   74	20	2	localObject3	Object
    //   95	4	2	localObject4	Object
    //   138	1	2	localUnsupportedOperationException	UnsupportedOperationException
    //   142	1	2	localIOException2	java.io.IOException
    //   146	1	2	localIOException3	java.io.IOException
    // Exception table:
    //   from	to	target	type
    //   22	32	74	finally
    //   32	42	74	finally
    //   10	18	95	finally
    //   42	60	95	finally
    //   60	62	95	finally
    //   75	95	95	finally
    //   96	98	95	finally
    //   0	10	100	java/io/IOException
    //   98	100	100	java/io/IOException
    //   0	10	124	finally
    //   98	100	124	finally
    //   101	112	124	finally
    //   22	32	138	java/lang/UnsupportedOperationException
    //   32	42	138	java/lang/UnsupportedOperationException
    //   32	42	142	java/io/IOException
    //   22	32	146	java/io/IOException
  }
}

/* Location:
 * Qualified Name:     com.b.a.g
 * Java Class Version: 6 (50.0)
 * JD-Core Version:    0.7.1
 */