package com.b.a;

final class h
  implements Runnable
{
  h(q paramq, byte[] paramArrayOfByte) {}
  
  /* Error */
  public final void run()
  {
    // Byte code:
    //   0: aload_0
    //   1: getfield 14	com/b/a/h:b	Lcom/b/a/q;
    //   4: getfield 29	com/b/a/q:h	Ljava/lang/Object;
    //   7: astore_1
    //   8: aload_1
    //   9: monitorenter
    //   10: aload_0
    //   11: getfield 14	com/b/a/h:b	Lcom/b/a/q;
    //   14: getfield 33	com/b/a/q:c	Ljava/net/Socket;
    //   17: ifnonnull +6 -> 23
    //   20: aload_1
    //   21: monitorexit
    //   22: return
    //   23: aload_1
    //   24: monitorexit
    //   25: aload_0
    //   26: getfield 14	com/b/a/h:b	Lcom/b/a/q;
    //   29: getfield 33	com/b/a/q:c	Ljava/net/Socket;
    //   32: invokevirtual 39	java/net/Socket:getOutputStream	()Ljava/io/OutputStream;
    //   35: astore_1
    //   36: aload_1
    //   37: aload_0
    //   38: getfield 16	com/b/a/h:a	[B
    //   41: invokevirtual 45	java/io/OutputStream:write	([B)V
    //   44: aload_1
    //   45: invokevirtual 48	java/io/OutputStream:flush	()V
    //   48: return
    //   49: astore_1
    //   50: aload_0
    //   51: getfield 14	com/b/a/h:b	Lcom/b/a/q;
    //   54: getfield 51	com/b/a/q:b	Lcom/b/a/p;
    //   57: aload_1
    //   58: invokevirtual 57	com/b/a/p:onError	(Ljava/lang/Exception;)V
    //   61: return
    //   62: astore_2
    //   63: aload_1
    //   64: monitorexit
    //   65: aload_2
    //   66: athrow
    // Local variable table:
    //   start	length	slot	name	signature
    //   0	67	0	this	h
    //   49	15	1	localIOException	java.io.IOException
    //   62	4	2	localObject2	Object
    // Exception table:
    //   from	to	target	type
    //   0	10	49	java/io/IOException
    //   25	48	49	java/io/IOException
    //   65	67	49	java/io/IOException
    //   10	22	62	finally
    //   23	25	62	finally
    //   63	65	62	finally
  }
}

/* Location:
 * Qualified Name:     com.b.a.h
 * Java Class Version: 6 (50.0)
 * JD-Core Version:    0.7.1
 */