package b;

import b.a.b.s;

final class am
  implements g
{
  final ai a;
  boolean b;
  volatile boolean c;
  ao d;
  s e;
  
  protected am(ai paramai, ao paramao)
  {
    a = paramai;
    d = paramao;
  }
  
  /* Error */
  final at a(ao paramao, boolean paramBoolean)
  {
    // Byte code:
    //   0: aload_1
    //   1: getfield 37	b/ao:d	Lb/ar;
    //   4: astore 16
    //   6: aload 16
    //   8: ifnull +3230 -> 3238
    //   11: aload_1
    //   12: invokevirtual 40	b/ao:a	()Lb/an;
    //   15: astore_1
    //   16: aload 16
    //   18: invokevirtual 45	b/ar:a	()Lb/af;
    //   21: astore 17
    //   23: aload 17
    //   25: ifnull +15 -> 40
    //   28: aload_1
    //   29: ldc 47
    //   31: aload 17
    //   33: invokevirtual 53	b/af:toString	()Ljava/lang/String;
    //   36: invokevirtual 58	b/an:a	(Ljava/lang/String;Ljava/lang/String;)Lb/an;
    //   39: pop
    //   40: aload 16
    //   42: invokevirtual 61	b/ar:b	()J
    //   45: lstore 6
    //   47: lload 6
    //   49: ldc2_w 62
    //   52: lcmp
    //   53: ifeq +76 -> 129
    //   56: aload_1
    //   57: ldc 65
    //   59: lload 6
    //   61: invokestatic 70	java/lang/Long:toString	(J)Ljava/lang/String;
    //   64: invokevirtual 58	b/an:a	(Ljava/lang/String;Ljava/lang/String;)Lb/an;
    //   67: pop
    //   68: aload_1
    //   69: ldc 72
    //   71: invokevirtual 75	b/an:a	(Ljava/lang/String;)Lb/an;
    //   74: pop
    //   75: aload_1
    //   76: invokevirtual 78	b/an:a	()Lb/ao;
    //   79: astore_1
    //   80: aload_0
    //   81: new 80	b/a/b/s
    //   84: dup
    //   85: aload_0
    //   86: getfield 22	b/am:a	Lb/ai;
    //   89: aload_1
    //   90: iconst_0
    //   91: iconst_0
    //   92: iload_2
    //   93: aconst_null
    //   94: aconst_null
    //   95: aconst_null
    //   96: invokespecial 83	b/a/b/s:<init>	(Lb/ai;Lb/ao;ZZZLb/a/b/ad;Lb/a/b/z;Lb/at;)V
    //   99: putfield 85	b/am:e	Lb/a/b/s;
    //   102: iconst_0
    //   103: istore 4
    //   105: aload_0
    //   106: getfield 87	b/am:c	Z
    //   109: ifeq +39 -> 148
    //   112: aload_0
    //   113: getfield 85	b/am:e	Lb/a/b/s;
    //   116: invokevirtual 89	b/a/b/s:b	()V
    //   119: new 32	java/io/IOException
    //   122: dup
    //   123: ldc 91
    //   125: invokespecial 94	java/io/IOException:<init>	(Ljava/lang/String;)V
    //   128: athrow
    //   129: aload_1
    //   130: ldc 72
    //   132: ldc 96
    //   134: invokevirtual 58	b/an:a	(Ljava/lang/String;Ljava/lang/String;)Lb/an;
    //   137: pop
    //   138: aload_1
    //   139: ldc 65
    //   141: invokevirtual 75	b/an:a	(Ljava/lang/String;)Lb/an;
    //   144: pop
    //   145: goto -70 -> 75
    //   148: aload_0
    //   149: getfield 85	b/am:e	Lb/a/b/s;
    //   152: astore 18
    //   154: aload 18
    //   156: getfield 100	b/a/b/s:r	Lb/a/b/c;
    //   159: ifnonnull +427 -> 586
    //   162: aload 18
    //   164: getfield 103	b/a/b/s:e	Lb/a/b/u;
    //   167: ifnull +36 -> 203
    //   170: new 105	java/lang/IllegalStateException
    //   173: dup
    //   174: invokespecial 106	java/lang/IllegalStateException:<init>	()V
    //   177: athrow
    //   178: astore_1
    //   179: aload_1
    //   180: invokevirtual 109	b/a/b/x:a	()Ljava/io/IOException;
    //   183: athrow
    //   184: astore_1
    //   185: iconst_1
    //   186: istore_3
    //   187: iload_3
    //   188: ifeq +13 -> 201
    //   191: aload_0
    //   192: getfield 85	b/am:e	Lb/a/b/s;
    //   195: invokevirtual 112	b/a/b/s:c	()Lb/a/b/ad;
    //   198: invokevirtual 116	b/a/b/ad:c	()V
    //   201: aload_1
    //   202: athrow
    //   203: aload 18
    //   205: getfield 119	b/a/b/s:i	Lb/ao;
    //   208: astore_1
    //   209: aload_1
    //   210: invokevirtual 40	b/ao:a	()Lb/an;
    //   213: astore 16
    //   215: aload_1
    //   216: ldc 121
    //   218: invokevirtual 124	b/ao:a	(Ljava/lang/String;)Ljava/lang/String;
    //   221: ifnonnull +19 -> 240
    //   224: aload 16
    //   226: ldc 121
    //   228: aload_1
    //   229: getfield 127	b/ao:a	Lb/ac;
    //   232: iconst_0
    //   233: invokestatic 132	b/a/p:a	(Lb/ac;Z)Ljava/lang/String;
    //   236: invokevirtual 58	b/an:a	(Ljava/lang/String;Ljava/lang/String;)Lb/an;
    //   239: pop
    //   240: aload_1
    //   241: ldc -122
    //   243: invokevirtual 124	b/ao:a	(Ljava/lang/String;)Ljava/lang/String;
    //   246: ifnonnull +13 -> 259
    //   249: aload 16
    //   251: ldc -122
    //   253: ldc -120
    //   255: invokevirtual 58	b/an:a	(Ljava/lang/String;Ljava/lang/String;)Lb/an;
    //   258: pop
    //   259: aload_1
    //   260: ldc -118
    //   262: invokevirtual 124	b/ao:a	(Ljava/lang/String;)Ljava/lang/String;
    //   265: ifnonnull +19 -> 284
    //   268: aload 18
    //   270: iconst_1
    //   271: putfield 141	b/a/b/s:g	Z
    //   274: aload 16
    //   276: ldc -118
    //   278: ldc -113
    //   280: invokevirtual 58	b/an:a	(Ljava/lang/String;Ljava/lang/String;)Lb/an;
    //   283: pop
    //   284: aload 18
    //   286: getfield 145	b/a/b/s:b	Lb/ai;
    //   289: getfield 151	b/ai:h	Lb/t;
    //   292: invokeinterface 156 1 0
    //   297: astore 17
    //   299: aload 17
    //   301: invokeinterface 162 1 0
    //   306: ifne +16 -> 322
    //   309: aload 16
    //   311: ldc -92
    //   313: aload 17
    //   315: invokestatic 167	b/a/b/s:a	(Ljava/util/List;)Ljava/lang/String;
    //   318: invokevirtual 58	b/an:a	(Ljava/lang/String;Ljava/lang/String;)Lb/an;
    //   321: pop
    //   322: aload_1
    //   323: ldc -87
    //   325: invokevirtual 124	b/ao:a	(Ljava/lang/String;)Ljava/lang/String;
    //   328: ifnonnull +13 -> 341
    //   331: aload 16
    //   333: ldc -87
    //   335: ldc -85
    //   337: invokevirtual 58	b/an:a	(Ljava/lang/String;Ljava/lang/String;)Lb/an;
    //   340: pop
    //   341: aload 16
    //   343: invokevirtual 78	b/an:a	()Lb/ao;
    //   346: astore 19
    //   348: getstatic 176	b/a/f:b	Lb/a/f;
    //   351: aload 18
    //   353: getfield 145	b/a/b/s:b	Lb/ai;
    //   356: invokevirtual 179	b/a/f:a	(Lb/ai;)Lb/a/g;
    //   359: astore_1
    //   360: aload_1
    //   361: ifnull +300 -> 661
    //   364: aload_1
    //   365: invokeinterface 184 1 0
    //   370: astore 16
    //   372: new 186	b/a/b/b
    //   375: dup
    //   376: invokestatic 191	java/lang/System:currentTimeMillis	()J
    //   379: aload 19
    //   381: aload 16
    //   383: invokespecial 194	b/a/b/b:<init>	(JLb/ao;Lb/at;)V
    //   386: astore 20
    //   388: aload 20
    //   390: getfield 197	b/a/b/b:c	Lb/at;
    //   393: ifnonnull +274 -> 667
    //   396: new 199	b/a/b/c
    //   399: dup
    //   400: aload 20
    //   402: getfield 201	b/a/b/b:b	Lb/ao;
    //   405: aconst_null
    //   406: iconst_0
    //   407: invokespecial 204	b/a/b/c:<init>	(Lb/ao;Lb/at;B)V
    //   410: astore_1
    //   411: aload_1
    //   412: astore 17
    //   414: aload_1
    //   415: getfield 206	b/a/b/c:a	Lb/ao;
    //   418: ifnull +32 -> 450
    //   421: aload_1
    //   422: astore 17
    //   424: aload 20
    //   426: getfield 201	b/a/b/b:b	Lb/ao;
    //   429: invokevirtual 209	b/ao:b	()Lb/f;
    //   432: getfield 214	b/f:k	Z
    //   435: ifeq +15 -> 450
    //   438: new 199	b/a/b/c
    //   441: dup
    //   442: aconst_null
    //   443: aconst_null
    //   444: iconst_0
    //   445: invokespecial 204	b/a/b/c:<init>	(Lb/ao;Lb/at;B)V
    //   448: astore 17
    //   450: aload 18
    //   452: aload 17
    //   454: putfield 100	b/a/b/s:r	Lb/a/b/c;
    //   457: aload 18
    //   459: aload 18
    //   461: getfield 100	b/a/b/s:r	Lb/a/b/c;
    //   464: getfield 206	b/a/b/c:a	Lb/ao;
    //   467: putfield 217	b/a/b/s:j	Lb/ao;
    //   470: aload 18
    //   472: aload 18
    //   474: getfield 100	b/a/b/s:r	Lb/a/b/c;
    //   477: getfield 219	b/a/b/c:b	Lb/at;
    //   480: putfield 221	b/a/b/s:k	Lb/at;
    //   483: aload 16
    //   485: ifnull +19 -> 504
    //   488: aload 18
    //   490: getfield 221	b/a/b/s:k	Lb/at;
    //   493: ifnonnull +11 -> 504
    //   496: aload 16
    //   498: getfield 226	b/at:g	Lb/au;
    //   501: invokestatic 229	b/a/p:a	(Ljava/io/Closeable;)V
    //   504: aload 18
    //   506: getfield 217	b/a/b/s:j	Lb/ao;
    //   509: ifnonnull +948 -> 1457
    //   512: aload 18
    //   514: getfield 221	b/a/b/s:k	Lb/at;
    //   517: ifnonnull +940 -> 1457
    //   520: new 231	b/as
    //   523: dup
    //   524: invokespecial 232	b/as:<init>	()V
    //   527: astore_1
    //   528: aload_1
    //   529: aload 18
    //   531: getfield 119	b/a/b/s:i	Lb/ao;
    //   534: putfield 233	b/as:a	Lb/ao;
    //   537: aload_1
    //   538: aload 18
    //   540: getfield 235	b/a/b/s:d	Lb/at;
    //   543: invokestatic 238	b/a/b/s:a	(Lb/at;)Lb/at;
    //   546: invokevirtual 241	b/as:c	(Lb/at;)Lb/as;
    //   549: astore_1
    //   550: aload_1
    //   551: getstatic 246	b/aj:b	Lb/aj;
    //   554: putfield 247	b/as:b	Lb/aj;
    //   557: aload_1
    //   558: sipush 504
    //   561: putfield 250	b/as:c	I
    //   564: aload_1
    //   565: ldc -4
    //   567: putfield 255	b/as:d	Ljava/lang/String;
    //   570: aload_1
    //   571: getstatic 257	b/a/b/s:a	Lb/au;
    //   574: putfield 258	b/as:g	Lb/au;
    //   577: aload 18
    //   579: aload_1
    //   580: invokevirtual 259	b/as:a	()Lb/at;
    //   583: putfield 262	b/a/b/s:l	Lb/at;
    //   586: aload_0
    //   587: getfield 85	b/am:e	Lb/a/b/s;
    //   590: astore 17
    //   592: aload 17
    //   594: getfield 262	b/a/b/s:l	Lb/at;
    //   597: ifnonnull +1408 -> 2005
    //   600: aload 17
    //   602: getfield 217	b/a/b/s:j	Lb/ao;
    //   605: ifnonnull +1198 -> 1803
    //   608: aload 17
    //   610: getfield 221	b/a/b/s:k	Lb/at;
    //   613: ifnonnull +1190 -> 1803
    //   616: new 105	java/lang/IllegalStateException
    //   619: dup
    //   620: ldc_w 264
    //   623: invokespecial 265	java/lang/IllegalStateException:<init>	(Ljava/lang/String;)V
    //   626: athrow
    //   627: astore_1
    //   628: aload_0
    //   629: getfield 85	b/am:e	Lb/a/b/s;
    //   632: aload_1
    //   633: getfield 268	b/a/b/aa:b	Ljava/io/IOException;
    //   636: invokevirtual 271	b/a/b/s:a	(Ljava/io/IOException;)Lb/a/b/s;
    //   639: astore 16
    //   641: aload 16
    //   643: ifnull +1978 -> 2621
    //   646: aload_0
    //   647: aload 16
    //   649: putfield 85	b/am:e	Lb/a/b/s;
    //   652: goto -547 -> 105
    //   655: iconst_0
    //   656: istore_3
    //   657: astore_1
    //   658: goto -471 -> 187
    //   661: aconst_null
    //   662: astore 16
    //   664: goto -292 -> 372
    //   667: aload 20
    //   669: getfield 201	b/a/b/b:b	Lb/ao;
    //   672: invokevirtual 273	b/ao:c	()Z
    //   675: ifeq +57 -> 732
    //   678: aload 20
    //   680: getfield 197	b/a/b/b:c	Lb/at;
    //   683: getfield 276	b/at:e	Lb/x;
    //   686: ifnonnull +46 -> 732
    //   689: new 199	b/a/b/c
    //   692: dup
    //   693: aload 20
    //   695: getfield 201	b/a/b/b:b	Lb/ao;
    //   698: aconst_null
    //   699: iconst_0
    //   700: invokespecial 204	b/a/b/c:<init>	(Lb/ao;Lb/at;B)V
    //   703: astore_1
    //   704: goto -293 -> 411
    //   707: astore_1
    //   708: aload_0
    //   709: getfield 85	b/am:e	Lb/a/b/s;
    //   712: aload_1
    //   713: invokevirtual 271	b/a/b/s:a	(Ljava/io/IOException;)Lb/a/b/s;
    //   716: astore 16
    //   718: aload 16
    //   720: ifnull +1906 -> 2626
    //   723: aload_0
    //   724: aload 16
    //   726: putfield 85	b/am:e	Lb/a/b/s;
    //   729: goto -624 -> 105
    //   732: aload 20
    //   734: getfield 197	b/a/b/b:c	Lb/at;
    //   737: aload 20
    //   739: getfield 201	b/a/b/b:b	Lb/ao;
    //   742: invokestatic 279	b/a/b/c:a	(Lb/at;Lb/ao;)Z
    //   745: ifne +21 -> 766
    //   748: new 199	b/a/b/c
    //   751: dup
    //   752: aload 20
    //   754: getfield 201	b/a/b/b:b	Lb/ao;
    //   757: aconst_null
    //   758: iconst_0
    //   759: invokespecial 204	b/a/b/c:<init>	(Lb/ao;Lb/at;B)V
    //   762: astore_1
    //   763: goto -352 -> 411
    //   766: aload 20
    //   768: getfield 201	b/a/b/b:b	Lb/ao;
    //   771: invokevirtual 209	b/ao:b	()Lb/f;
    //   774: astore 17
    //   776: aload 17
    //   778: getfield 280	b/f:c	Z
    //   781: ifne +14 -> 795
    //   784: aload 20
    //   786: getfield 201	b/a/b/b:b	Lb/ao;
    //   789: invokestatic 283	b/a/b/b:a	(Lb/ao;)Z
    //   792: ifeq +21 -> 813
    //   795: new 199	b/a/b/c
    //   798: dup
    //   799: aload 20
    //   801: getfield 201	b/a/b/b:b	Lb/ao;
    //   804: aconst_null
    //   805: iconst_0
    //   806: invokespecial 204	b/a/b/c:<init>	(Lb/ao;Lb/at;B)V
    //   809: astore_1
    //   810: goto -399 -> 411
    //   813: aload 20
    //   815: getfield 286	b/a/b/b:d	Ljava/util/Date;
    //   818: ifnull +2423 -> 3241
    //   821: lconst_0
    //   822: aload 20
    //   824: getfield 289	b/a/b/b:j	J
    //   827: aload 20
    //   829: getfield 286	b/a/b/b:d	Ljava/util/Date;
    //   832: invokevirtual 294	java/util/Date:getTime	()J
    //   835: lsub
    //   836: invokestatic 300	java/lang/Math:max	(JJ)J
    //   839: lstore 6
    //   841: lload 6
    //   843: lstore 8
    //   845: aload 20
    //   847: getfield 302	b/a/b/b:l	I
    //   850: iconst_m1
    //   851: if_icmpeq +22 -> 873
    //   854: lload 6
    //   856: getstatic 308	java/util/concurrent/TimeUnit:SECONDS	Ljava/util/concurrent/TimeUnit;
    //   859: aload 20
    //   861: getfield 302	b/a/b/b:l	I
    //   864: i2l
    //   865: invokevirtual 312	java/util/concurrent/TimeUnit:toMillis	(J)J
    //   868: invokestatic 300	java/lang/Math:max	(JJ)J
    //   871: lstore 8
    //   873: lload 8
    //   875: aload 20
    //   877: getfield 289	b/a/b/b:j	J
    //   880: aload 20
    //   882: getfield 314	b/a/b/b:i	J
    //   885: lsub
    //   886: ladd
    //   887: aload 20
    //   889: getfield 316	b/a/b/b:a	J
    //   892: aload 20
    //   894: getfield 289	b/a/b/b:j	J
    //   897: lsub
    //   898: ladd
    //   899: lstore 14
    //   901: aload 20
    //   903: getfield 197	b/a/b/b:c	Lb/at;
    //   906: invokevirtual 317	b/at:b	()Lb/f;
    //   909: astore_1
    //   910: aload_1
    //   911: getfield 319	b/f:e	I
    //   914: iconst_m1
    //   915: if_icmpeq +235 -> 1150
    //   918: getstatic 308	java/util/concurrent/TimeUnit:SECONDS	Ljava/util/concurrent/TimeUnit;
    //   921: aload_1
    //   922: getfield 319	b/f:e	I
    //   925: i2l
    //   926: invokevirtual 312	java/util/concurrent/TimeUnit:toMillis	(J)J
    //   929: lstore 6
    //   931: aload 17
    //   933: getfield 319	b/f:e	I
    //   936: iconst_m1
    //   937: if_icmpeq +2298 -> 3235
    //   940: lload 6
    //   942: getstatic 308	java/util/concurrent/TimeUnit:SECONDS	Ljava/util/concurrent/TimeUnit;
    //   945: aload 17
    //   947: getfield 319	b/f:e	I
    //   950: i2l
    //   951: invokevirtual 312	java/util/concurrent/TimeUnit:toMillis	(J)J
    //   954: invokestatic 322	java/lang/Math:min	(JJ)J
    //   957: lstore 6
    //   959: aload 17
    //   961: getfield 324	b/f:j	I
    //   964: iconst_m1
    //   965: if_icmpeq +2264 -> 3229
    //   968: getstatic 308	java/util/concurrent/TimeUnit:SECONDS	Ljava/util/concurrent/TimeUnit;
    //   971: aload 17
    //   973: getfield 324	b/f:j	I
    //   976: i2l
    //   977: invokevirtual 312	java/util/concurrent/TimeUnit:toMillis	(J)J
    //   980: lstore 8
    //   982: lconst_0
    //   983: lstore 12
    //   985: aload 20
    //   987: getfield 197	b/a/b/b:c	Lb/at;
    //   990: invokevirtual 317	b/at:b	()Lb/f;
    //   993: astore_1
    //   994: lload 12
    //   996: lstore 10
    //   998: aload_1
    //   999: getfield 326	b/f:h	Z
    //   1002: ifne +30 -> 1032
    //   1005: lload 12
    //   1007: lstore 10
    //   1009: aload 17
    //   1011: getfield 328	b/f:i	I
    //   1014: iconst_m1
    //   1015: if_icmpeq +17 -> 1032
    //   1018: getstatic 308	java/util/concurrent/TimeUnit:SECONDS	Ljava/util/concurrent/TimeUnit;
    //   1021: aload 17
    //   1023: getfield 328	b/f:i	I
    //   1026: i2l
    //   1027: invokevirtual 312	java/util/concurrent/TimeUnit:toMillis	(J)J
    //   1030: lstore 10
    //   1032: aload_1
    //   1033: getfield 280	b/f:c	Z
    //   1036: ifne +299 -> 1335
    //   1039: lload 14
    //   1041: lload 8
    //   1043: ladd
    //   1044: lload 10
    //   1046: lload 6
    //   1048: ladd
    //   1049: lcmp
    //   1050: ifge +285 -> 1335
    //   1053: aload 20
    //   1055: getfield 197	b/a/b/b:c	Lb/at;
    //   1058: invokevirtual 331	b/at:a	()Lb/as;
    //   1061: astore_1
    //   1062: lload 8
    //   1064: lload 14
    //   1066: ladd
    //   1067: lload 6
    //   1069: lcmp
    //   1070: iflt +14 -> 1084
    //   1073: aload_1
    //   1074: ldc_w 333
    //   1077: ldc_w 335
    //   1080: invokevirtual 338	b/as:b	(Ljava/lang/String;Ljava/lang/String;)Lb/as;
    //   1083: pop
    //   1084: lload 14
    //   1086: ldc2_w 339
    //   1089: lcmp
    //   1090: ifle +43 -> 1133
    //   1093: aload 20
    //   1095: getfield 197	b/a/b/b:c	Lb/at;
    //   1098: invokevirtual 317	b/at:b	()Lb/f;
    //   1101: getfield 319	b/f:e	I
    //   1104: iconst_m1
    //   1105: if_icmpne +2154 -> 3259
    //   1108: aload 20
    //   1110: getfield 342	b/a/b/b:h	Ljava/util/Date;
    //   1113: ifnonnull +2146 -> 3259
    //   1116: iconst_1
    //   1117: istore_3
    //   1118: iload_3
    //   1119: ifeq +14 -> 1133
    //   1122: aload_1
    //   1123: ldc_w 333
    //   1126: ldc_w 344
    //   1129: invokevirtual 338	b/as:b	(Ljava/lang/String;Ljava/lang/String;)Lb/as;
    //   1132: pop
    //   1133: new 199	b/a/b/c
    //   1136: dup
    //   1137: aconst_null
    //   1138: aload_1
    //   1139: invokevirtual 259	b/as:a	()Lb/at;
    //   1142: iconst_0
    //   1143: invokespecial 204	b/a/b/c:<init>	(Lb/ao;Lb/at;B)V
    //   1146: astore_1
    //   1147: goto -736 -> 411
    //   1150: aload 20
    //   1152: getfield 342	b/a/b/b:h	Ljava/util/Date;
    //   1155: ifnull +61 -> 1216
    //   1158: aload 20
    //   1160: getfield 286	b/a/b/b:d	Ljava/util/Date;
    //   1163: ifnull +43 -> 1206
    //   1166: aload 20
    //   1168: getfield 286	b/a/b/b:d	Ljava/util/Date;
    //   1171: invokevirtual 294	java/util/Date:getTime	()J
    //   1174: lstore 6
    //   1176: aload 20
    //   1178: getfield 342	b/a/b/b:h	Ljava/util/Date;
    //   1181: invokevirtual 294	java/util/Date:getTime	()J
    //   1184: lload 6
    //   1186: lsub
    //   1187: lstore 8
    //   1189: lload 8
    //   1191: lstore 6
    //   1193: lload 8
    //   1195: lconst_0
    //   1196: lcmp
    //   1197: ifgt -266 -> 931
    //   1200: lconst_0
    //   1201: lstore 6
    //   1203: goto -272 -> 931
    //   1206: aload 20
    //   1208: getfield 289	b/a/b/b:j	J
    //   1211: lstore 6
    //   1213: goto -37 -> 1176
    //   1216: aload 20
    //   1218: getfield 347	b/a/b/b:f	Ljava/util/Date;
    //   1221: ifnull +2032 -> 3253
    //   1224: aload 20
    //   1226: getfield 197	b/a/b/b:c	Lb/at;
    //   1229: getfield 348	b/at:a	Lb/ao;
    //   1232: getfield 127	b/ao:a	Lb/ac;
    //   1235: astore_1
    //   1236: aload_1
    //   1237: getfield 353	b/ac:d	Ljava/util/List;
    //   1240: ifnonnull +58 -> 1298
    //   1243: aconst_null
    //   1244: astore_1
    //   1245: aload_1
    //   1246: ifnonnull +2007 -> 3253
    //   1249: aload 20
    //   1251: getfield 286	b/a/b/b:d	Ljava/util/Date;
    //   1254: ifnull +71 -> 1325
    //   1257: aload 20
    //   1259: getfield 286	b/a/b/b:d	Ljava/util/Date;
    //   1262: invokevirtual 294	java/util/Date:getTime	()J
    //   1265: lstore 6
    //   1267: lload 6
    //   1269: aload 20
    //   1271: getfield 347	b/a/b/b:f	Ljava/util/Date;
    //   1274: invokevirtual 294	java/util/Date:getTime	()J
    //   1277: lsub
    //   1278: lstore 6
    //   1280: lload 6
    //   1282: lconst_0
    //   1283: lcmp
    //   1284: ifle +1963 -> 3247
    //   1287: lload 6
    //   1289: ldc2_w 354
    //   1292: ldiv
    //   1293: lstore 6
    //   1295: goto -364 -> 931
    //   1298: new 357	java/lang/StringBuilder
    //   1301: dup
    //   1302: invokespecial 358	java/lang/StringBuilder:<init>	()V
    //   1305: astore 21
    //   1307: aload 21
    //   1309: aload_1
    //   1310: getfield 353	b/ac:d	Ljava/util/List;
    //   1313: invokestatic 361	b/ac:b	(Ljava/lang/StringBuilder;Ljava/util/List;)V
    //   1316: aload 21
    //   1318: invokevirtual 362	java/lang/StringBuilder:toString	()Ljava/lang/String;
    //   1321: astore_1
    //   1322: goto -77 -> 1245
    //   1325: aload 20
    //   1327: getfield 314	b/a/b/b:i	J
    //   1330: lstore 6
    //   1332: goto -65 -> 1267
    //   1335: aload 20
    //   1337: getfield 201	b/a/b/b:b	Lb/ao;
    //   1340: invokevirtual 40	b/ao:a	()Lb/an;
    //   1343: astore_1
    //   1344: aload 20
    //   1346: getfield 364	b/a/b/b:k	Ljava/lang/String;
    //   1349: ifnull +46 -> 1395
    //   1352: aload_1
    //   1353: ldc_w 366
    //   1356: aload 20
    //   1358: getfield 364	b/a/b/b:k	Ljava/lang/String;
    //   1361: invokevirtual 58	b/an:a	(Ljava/lang/String;Ljava/lang/String;)Lb/an;
    //   1364: pop
    //   1365: aload_1
    //   1366: invokevirtual 78	b/an:a	()Lb/ao;
    //   1369: astore_1
    //   1370: aload_1
    //   1371: invokestatic 283	b/a/b/b:a	(Lb/ao;)Z
    //   1374: ifeq +69 -> 1443
    //   1377: new 199	b/a/b/c
    //   1380: dup
    //   1381: aload_1
    //   1382: aload 20
    //   1384: getfield 197	b/a/b/b:c	Lb/at;
    //   1387: iconst_0
    //   1388: invokespecial 204	b/a/b/c:<init>	(Lb/ao;Lb/at;B)V
    //   1391: astore_1
    //   1392: goto -981 -> 411
    //   1395: aload 20
    //   1397: getfield 347	b/a/b/b:f	Ljava/util/Date;
    //   1400: ifnull +19 -> 1419
    //   1403: aload_1
    //   1404: ldc_w 368
    //   1407: aload 20
    //   1409: getfield 370	b/a/b/b:g	Ljava/lang/String;
    //   1412: invokevirtual 58	b/an:a	(Ljava/lang/String;Ljava/lang/String;)Lb/an;
    //   1415: pop
    //   1416: goto -51 -> 1365
    //   1419: aload 20
    //   1421: getfield 286	b/a/b/b:d	Ljava/util/Date;
    //   1424: ifnull -59 -> 1365
    //   1427: aload_1
    //   1428: ldc_w 368
    //   1431: aload 20
    //   1433: getfield 372	b/a/b/b:e	Ljava/lang/String;
    //   1436: invokevirtual 58	b/an:a	(Ljava/lang/String;Ljava/lang/String;)Lb/an;
    //   1439: pop
    //   1440: goto -75 -> 1365
    //   1443: new 199	b/a/b/c
    //   1446: dup
    //   1447: aload_1
    //   1448: aconst_null
    //   1449: iconst_0
    //   1450: invokespecial 204	b/a/b/c:<init>	(Lb/ao;Lb/at;B)V
    //   1453: astore_1
    //   1454: goto -1043 -> 411
    //   1457: aload 18
    //   1459: getfield 217	b/a/b/s:j	Lb/ao;
    //   1462: ifnonnull +70 -> 1532
    //   1465: aload 18
    //   1467: getfield 221	b/a/b/s:k	Lb/at;
    //   1470: invokevirtual 331	b/at:a	()Lb/as;
    //   1473: astore_1
    //   1474: aload_1
    //   1475: aload 18
    //   1477: getfield 119	b/a/b/s:i	Lb/ao;
    //   1480: putfield 233	b/as:a	Lb/ao;
    //   1483: aload 18
    //   1485: aload_1
    //   1486: aload 18
    //   1488: getfield 235	b/a/b/s:d	Lb/at;
    //   1491: invokestatic 238	b/a/b/s:a	(Lb/at;)Lb/at;
    //   1494: invokevirtual 241	b/as:c	(Lb/at;)Lb/as;
    //   1497: aload 18
    //   1499: getfield 221	b/a/b/s:k	Lb/at;
    //   1502: invokestatic 238	b/a/b/s:a	(Lb/at;)Lb/at;
    //   1505: invokevirtual 374	b/as:b	(Lb/at;)Lb/as;
    //   1508: invokevirtual 259	b/as:a	()Lb/at;
    //   1511: putfield 262	b/a/b/s:l	Lb/at;
    //   1514: aload 18
    //   1516: aload 18
    //   1518: aload 18
    //   1520: getfield 262	b/a/b/s:l	Lb/at;
    //   1523: invokevirtual 376	b/a/b/s:b	(Lb/at;)Lb/at;
    //   1526: putfield 262	b/a/b/s:l	Lb/at;
    //   1529: goto -943 -> 586
    //   1532: aload 18
    //   1534: getfield 217	b/a/b/s:j	Lb/ao;
    //   1537: getfield 378	b/ao:b	Ljava/lang/String;
    //   1540: ldc_w 380
    //   1543: invokevirtual 386	java/lang/String:equals	(Ljava/lang/Object;)Z
    //   1546: ifne +149 -> 1695
    //   1549: iconst_1
    //   1550: istore 5
    //   1552: aload 18
    //   1554: aload 18
    //   1556: getfield 389	b/a/b/s:c	Lb/a/b/ad;
    //   1559: aload 18
    //   1561: getfield 145	b/a/b/s:b	Lb/ai;
    //   1564: getfield 392	b/ai:w	I
    //   1567: aload 18
    //   1569: getfield 145	b/a/b/s:b	Lb/ai;
    //   1572: getfield 395	b/ai:x	I
    //   1575: aload 18
    //   1577: getfield 145	b/a/b/s:b	Lb/ai;
    //   1580: getfield 398	b/ai:y	I
    //   1583: aload 18
    //   1585: getfield 145	b/a/b/s:b	Lb/ai;
    //   1588: getfield 401	b/ai:v	Z
    //   1591: iload 5
    //   1593: invokevirtual 404	b/a/b/ad:a	(IIIZZ)Lb/a/b/u;
    //   1596: putfield 103	b/a/b/s:e	Lb/a/b/u;
    //   1599: aload 18
    //   1601: getfield 103	b/a/b/s:e	Lb/a/b/u;
    //   1604: aload 18
    //   1606: invokeinterface 409 2 0
    //   1611: aload 18
    //   1613: getfield 412	b/a/b/s:o	Z
    //   1616: ifeq +85 -> 1701
    //   1619: aload 18
    //   1621: getfield 217	b/a/b/s:j	Lb/ao;
    //   1624: invokestatic 413	b/a/b/s:a	(Lb/ao;)Z
    //   1627: ifeq +74 -> 1701
    //   1630: aload 18
    //   1632: getfield 417	b/a/b/s:m	Lc/x;
    //   1635: ifnonnull +66 -> 1701
    //   1638: iconst_1
    //   1639: istore_3
    //   1640: iload_3
    //   1641: ifeq -1055 -> 586
    //   1644: aload 19
    //   1646: invokestatic 422	b/a/b/v:a	(Lb/ao;)J
    //   1649: lstore 6
    //   1651: aload 18
    //   1653: getfield 423	b/a/b/s:h	Z
    //   1656: ifeq +107 -> 1763
    //   1659: lload 6
    //   1661: ldc2_w 424
    //   1664: lcmp
    //   1665: ifle +41 -> 1706
    //   1668: new 105	java/lang/IllegalStateException
    //   1671: dup
    //   1672: ldc_w 427
    //   1675: invokespecial 265	java/lang/IllegalStateException:<init>	(Ljava/lang/String;)V
    //   1678: athrow
    //   1679: astore_1
    //   1680: aload 16
    //   1682: ifnull +11 -> 1693
    //   1685: aload 16
    //   1687: getfield 226	b/at:g	Lb/au;
    //   1690: invokestatic 229	b/a/p:a	(Ljava/io/Closeable;)V
    //   1693: aload_1
    //   1694: athrow
    //   1695: iconst_0
    //   1696: istore 5
    //   1698: goto -146 -> 1552
    //   1701: iconst_0
    //   1702: istore_3
    //   1703: goto -63 -> 1640
    //   1706: lload 6
    //   1708: ldc2_w 62
    //   1711: lcmp
    //   1712: ifeq +36 -> 1748
    //   1715: aload 18
    //   1717: getfield 103	b/a/b/s:e	Lb/a/b/u;
    //   1720: aload 18
    //   1722: getfield 217	b/a/b/s:j	Lb/ao;
    //   1725: invokeinterface 430 2 0
    //   1730: aload 18
    //   1732: new 432	b/a/b/z
    //   1735: dup
    //   1736: lload 6
    //   1738: l2i
    //   1739: invokespecial 435	b/a/b/z:<init>	(I)V
    //   1742: putfield 417	b/a/b/s:m	Lc/x;
    //   1745: goto -1159 -> 586
    //   1748: aload 18
    //   1750: new 432	b/a/b/z
    //   1753: dup
    //   1754: invokespecial 436	b/a/b/z:<init>	()V
    //   1757: putfield 417	b/a/b/s:m	Lc/x;
    //   1760: goto -1174 -> 586
    //   1763: aload 18
    //   1765: getfield 103	b/a/b/s:e	Lb/a/b/u;
    //   1768: aload 18
    //   1770: getfield 217	b/a/b/s:j	Lb/ao;
    //   1773: invokeinterface 430 2 0
    //   1778: aload 18
    //   1780: aload 18
    //   1782: getfield 103	b/a/b/s:e	Lb/a/b/u;
    //   1785: aload 18
    //   1787: getfield 217	b/a/b/s:j	Lb/ao;
    //   1790: lload 6
    //   1792: invokeinterface 439 4 0
    //   1797: putfield 417	b/a/b/s:m	Lc/x;
    //   1800: goto -1214 -> 586
    //   1803: aload 17
    //   1805: getfield 217	b/a/b/s:j	Lb/ao;
    //   1808: ifnull +197 -> 2005
    //   1811: aload 17
    //   1813: getfield 442	b/a/b/s:p	Z
    //   1816: ifeq +209 -> 2025
    //   1819: aload 17
    //   1821: getfield 103	b/a/b/s:e	Lb/a/b/u;
    //   1824: aload 17
    //   1826: getfield 217	b/a/b/s:j	Lb/ao;
    //   1829: invokeinterface 430 2 0
    //   1834: aload 17
    //   1836: invokevirtual 444	b/a/b/s:d	()Lb/at;
    //   1839: astore_1
    //   1840: aload 17
    //   1842: aload_1
    //   1843: getfield 447	b/at:f	Lb/z;
    //   1846: invokevirtual 450	b/a/b/s:a	(Lb/z;)V
    //   1849: aload 17
    //   1851: getfield 221	b/a/b/s:k	Lb/at;
    //   1854: ifnull +474 -> 2328
    //   1857: aload 17
    //   1859: getfield 221	b/a/b/s:k	Lb/at;
    //   1862: astore 16
    //   1864: aload_1
    //   1865: getfield 451	b/at:c	I
    //   1868: sipush 304
    //   1871: if_icmpne +392 -> 2263
    //   1874: iconst_1
    //   1875: istore_3
    //   1876: iload_3
    //   1877: ifeq +440 -> 2317
    //   1880: aload 17
    //   1882: getfield 221	b/a/b/s:k	Lb/at;
    //   1885: invokevirtual 331	b/at:a	()Lb/as;
    //   1888: astore 16
    //   1890: aload 16
    //   1892: aload 17
    //   1894: getfield 119	b/a/b/s:i	Lb/ao;
    //   1897: putfield 233	b/as:a	Lb/ao;
    //   1900: aload 17
    //   1902: aload 16
    //   1904: aload 17
    //   1906: getfield 235	b/a/b/s:d	Lb/at;
    //   1909: invokestatic 238	b/a/b/s:a	(Lb/at;)Lb/at;
    //   1912: invokevirtual 241	b/as:c	(Lb/at;)Lb/as;
    //   1915: aload 17
    //   1917: getfield 221	b/a/b/s:k	Lb/at;
    //   1920: getfield 447	b/at:f	Lb/z;
    //   1923: aload_1
    //   1924: getfield 447	b/at:f	Lb/z;
    //   1927: invokestatic 454	b/a/b/s:a	(Lb/z;Lb/z;)Lb/z;
    //   1930: invokevirtual 457	b/as:a	(Lb/z;)Lb/as;
    //   1933: aload 17
    //   1935: getfield 221	b/a/b/s:k	Lb/at;
    //   1938: invokestatic 238	b/a/b/s:a	(Lb/at;)Lb/at;
    //   1941: invokevirtual 374	b/as:b	(Lb/at;)Lb/as;
    //   1944: aload_1
    //   1945: invokestatic 238	b/a/b/s:a	(Lb/at;)Lb/at;
    //   1948: invokevirtual 459	b/as:a	(Lb/at;)Lb/as;
    //   1951: invokevirtual 259	b/as:a	()Lb/at;
    //   1954: putfield 262	b/a/b/s:l	Lb/at;
    //   1957: aload_1
    //   1958: getfield 226	b/at:g	Lb/au;
    //   1961: invokevirtual 464	b/au:close	()V
    //   1964: aload 17
    //   1966: invokevirtual 89	b/a/b/s:b	()V
    //   1969: getstatic 176	b/a/f:b	Lb/a/f;
    //   1972: aload 17
    //   1974: getfield 145	b/a/b/s:b	Lb/ai;
    //   1977: invokevirtual 179	b/a/f:a	(Lb/ai;)Lb/a/g;
    //   1980: pop
    //   1981: aload 17
    //   1983: getfield 262	b/a/b/s:l	Lb/at;
    //   1986: invokestatic 238	b/a/b/s:a	(Lb/at;)Lb/at;
    //   1989: pop
    //   1990: aload 17
    //   1992: aload 17
    //   1994: aload 17
    //   1996: getfield 262	b/a/b/s:l	Lb/at;
    //   1999: invokevirtual 376	b/a/b/s:b	(Lb/at;)Lb/at;
    //   2002: putfield 262	b/a/b/s:l	Lb/at;
    //   2005: aload_0
    //   2006: getfield 85	b/am:e	Lb/a/b/s;
    //   2009: astore_1
    //   2010: aload_1
    //   2011: getfield 262	b/a/b/s:l	Lb/at;
    //   2014: ifnonnull +614 -> 2628
    //   2017: new 105	java/lang/IllegalStateException
    //   2020: dup
    //   2021: invokespecial 106	java/lang/IllegalStateException:<init>	()V
    //   2024: athrow
    //   2025: aload 17
    //   2027: getfield 412	b/a/b/s:o	Z
    //   2030: ifne +30 -> 2060
    //   2033: new 466	b/a/b/r
    //   2036: dup
    //   2037: aload 17
    //   2039: iconst_0
    //   2040: aload 17
    //   2042: getfield 217	b/a/b/s:j	Lb/ao;
    //   2045: invokespecial 469	b/a/b/r:<init>	(Lb/a/b/s;ILb/ao;)V
    //   2048: aload 17
    //   2050: getfield 217	b/a/b/s:j	Lb/ao;
    //   2053: invokevirtual 472	b/a/b/r:a	(Lb/ao;)Lb/at;
    //   2056: astore_1
    //   2057: goto -217 -> 1840
    //   2060: aload 17
    //   2062: getfield 476	b/a/b/s:n	Lc/g;
    //   2065: ifnull +32 -> 2097
    //   2068: aload 17
    //   2070: getfield 476	b/a/b/s:n	Lc/g;
    //   2073: invokeinterface 481 1 0
    //   2078: getfield 485	c/f:b	J
    //   2081: lconst_0
    //   2082: lcmp
    //   2083: ifle +14 -> 2097
    //   2086: aload 17
    //   2088: getfield 476	b/a/b/s:n	Lc/g;
    //   2091: invokeinterface 488 1 0
    //   2096: pop
    //   2097: aload 17
    //   2099: getfield 490	b/a/b/s:f	J
    //   2102: ldc2_w 62
    //   2105: lcmp
    //   2106: ifne +86 -> 2192
    //   2109: aload 17
    //   2111: getfield 217	b/a/b/s:j	Lb/ao;
    //   2114: invokestatic 422	b/a/b/v:a	(Lb/ao;)J
    //   2117: ldc2_w 62
    //   2120: lcmp
    //   2121: ifne +56 -> 2177
    //   2124: aload 17
    //   2126: getfield 417	b/a/b/s:m	Lc/x;
    //   2129: instanceof 432
    //   2132: ifeq +45 -> 2177
    //   2135: aload 17
    //   2137: getfield 417	b/a/b/s:m	Lc/x;
    //   2140: checkcast 432	b/a/b/z
    //   2143: getfield 493	b/a/b/z:a	Lc/f;
    //   2146: getfield 485	c/f:b	J
    //   2149: lstore 6
    //   2151: aload 17
    //   2153: aload 17
    //   2155: getfield 217	b/a/b/s:j	Lb/ao;
    //   2158: invokevirtual 40	b/ao:a	()Lb/an;
    //   2161: ldc 65
    //   2163: lload 6
    //   2165: invokestatic 70	java/lang/Long:toString	(J)Ljava/lang/String;
    //   2168: invokevirtual 58	b/an:a	(Ljava/lang/String;Ljava/lang/String;)Lb/an;
    //   2171: invokevirtual 78	b/an:a	()Lb/ao;
    //   2174: putfield 217	b/a/b/s:j	Lb/ao;
    //   2177: aload 17
    //   2179: getfield 103	b/a/b/s:e	Lb/a/b/u;
    //   2182: aload 17
    //   2184: getfield 217	b/a/b/s:j	Lb/ao;
    //   2187: invokeinterface 430 2 0
    //   2192: aload 17
    //   2194: getfield 417	b/a/b/s:m	Lc/x;
    //   2197: ifnull -363 -> 1834
    //   2200: aload 17
    //   2202: getfield 476	b/a/b/s:n	Lc/g;
    //   2205: ifnull +45 -> 2250
    //   2208: aload 17
    //   2210: getfield 476	b/a/b/s:n	Lc/g;
    //   2213: invokeinterface 494 1 0
    //   2218: aload 17
    //   2220: getfield 417	b/a/b/s:m	Lc/x;
    //   2223: instanceof 432
    //   2226: ifeq -392 -> 1834
    //   2229: aload 17
    //   2231: getfield 103	b/a/b/s:e	Lb/a/b/u;
    //   2234: aload 17
    //   2236: getfield 417	b/a/b/s:m	Lc/x;
    //   2239: checkcast 432	b/a/b/z
    //   2242: invokeinterface 497 2 0
    //   2247: goto -413 -> 1834
    //   2250: aload 17
    //   2252: getfield 417	b/a/b/s:m	Lc/x;
    //   2255: invokeinterface 500 1 0
    //   2260: goto -42 -> 2218
    //   2263: aload 16
    //   2265: getfield 447	b/at:f	Lb/z;
    //   2268: ldc_w 502
    //   2271: invokevirtual 507	b/z:b	(Ljava/lang/String;)Ljava/util/Date;
    //   2274: astore 16
    //   2276: aload 16
    //   2278: ifnull +986 -> 3264
    //   2281: aload_1
    //   2282: getfield 447	b/at:f	Lb/z;
    //   2285: ldc_w 502
    //   2288: invokevirtual 507	b/z:b	(Ljava/lang/String;)Ljava/util/Date;
    //   2291: astore 18
    //   2293: aload 18
    //   2295: ifnull +969 -> 3264
    //   2298: aload 18
    //   2300: invokevirtual 294	java/util/Date:getTime	()J
    //   2303: aload 16
    //   2305: invokevirtual 294	java/util/Date:getTime	()J
    //   2308: lcmp
    //   2309: ifge +955 -> 3264
    //   2312: iconst_1
    //   2313: istore_3
    //   2314: goto -438 -> 1876
    //   2317: aload 17
    //   2319: getfield 221	b/a/b/s:k	Lb/at;
    //   2322: getfield 226	b/at:g	Lb/au;
    //   2325: invokestatic 229	b/a/p:a	(Ljava/io/Closeable;)V
    //   2328: aload_1
    //   2329: invokevirtual 331	b/at:a	()Lb/as;
    //   2332: astore 16
    //   2334: aload 16
    //   2336: aload 17
    //   2338: getfield 119	b/a/b/s:i	Lb/ao;
    //   2341: putfield 233	b/as:a	Lb/ao;
    //   2344: aload 17
    //   2346: aload 16
    //   2348: aload 17
    //   2350: getfield 235	b/a/b/s:d	Lb/at;
    //   2353: invokestatic 238	b/a/b/s:a	(Lb/at;)Lb/at;
    //   2356: invokevirtual 241	b/as:c	(Lb/at;)Lb/as;
    //   2359: aload 17
    //   2361: getfield 221	b/a/b/s:k	Lb/at;
    //   2364: invokestatic 238	b/a/b/s:a	(Lb/at;)Lb/at;
    //   2367: invokevirtual 374	b/as:b	(Lb/at;)Lb/as;
    //   2370: aload_1
    //   2371: invokestatic 238	b/a/b/s:a	(Lb/at;)Lb/at;
    //   2374: invokevirtual 459	b/as:a	(Lb/at;)Lb/as;
    //   2377: invokevirtual 259	b/as:a	()Lb/at;
    //   2380: putfield 262	b/a/b/s:l	Lb/at;
    //   2383: aload 17
    //   2385: getfield 262	b/a/b/s:l	Lb/at;
    //   2388: invokestatic 510	b/a/b/s:c	(Lb/at;)Z
    //   2391: ifeq -386 -> 2005
    //   2394: getstatic 176	b/a/f:b	Lb/a/f;
    //   2397: aload 17
    //   2399: getfield 145	b/a/b/s:b	Lb/ai;
    //   2402: invokevirtual 179	b/a/f:a	(Lb/ai;)Lb/a/g;
    //   2405: astore_1
    //   2406: aload_1
    //   2407: ifnull +76 -> 2483
    //   2410: aload 17
    //   2412: getfield 262	b/a/b/s:l	Lb/at;
    //   2415: aload 17
    //   2417: getfield 217	b/a/b/s:j	Lb/ao;
    //   2420: invokestatic 279	b/a/b/c:a	(Lb/at;Lb/ao;)Z
    //   2423: ifne +96 -> 2519
    //   2426: aload 17
    //   2428: getfield 217	b/a/b/s:j	Lb/ao;
    //   2431: getfield 378	b/ao:b	Ljava/lang/String;
    //   2434: astore_1
    //   2435: aload_1
    //   2436: ldc_w 512
    //   2439: invokevirtual 386	java/lang/String:equals	(Ljava/lang/Object;)Z
    //   2442: ifne +41 -> 2483
    //   2445: aload_1
    //   2446: ldc_w 514
    //   2449: invokevirtual 386	java/lang/String:equals	(Ljava/lang/Object;)Z
    //   2452: ifne +31 -> 2483
    //   2455: aload_1
    //   2456: ldc_w 516
    //   2459: invokevirtual 386	java/lang/String:equals	(Ljava/lang/Object;)Z
    //   2462: ifne +21 -> 2483
    //   2465: aload_1
    //   2466: ldc_w 518
    //   2469: invokevirtual 386	java/lang/String:equals	(Ljava/lang/Object;)Z
    //   2472: ifne +11 -> 2483
    //   2475: aload_1
    //   2476: ldc_w 520
    //   2479: invokevirtual 386	java/lang/String:equals	(Ljava/lang/Object;)Z
    //   2482: pop
    //   2483: aload 17
    //   2485: getfield 524	b/a/b/s:q	Lb/a/b/a;
    //   2488: astore 18
    //   2490: aload 17
    //   2492: getfield 262	b/a/b/s:l	Lb/at;
    //   2495: astore 16
    //   2497: aload 18
    //   2499: ifnonnull +43 -> 2542
    //   2502: aload 16
    //   2504: astore_1
    //   2505: aload 17
    //   2507: aload 17
    //   2509: aload_1
    //   2510: invokevirtual 376	b/a/b/s:b	(Lb/at;)Lb/at;
    //   2513: putfield 262	b/a/b/s:l	Lb/at;
    //   2516: goto -511 -> 2005
    //   2519: aload 17
    //   2521: getfield 262	b/a/b/s:l	Lb/at;
    //   2524: invokestatic 238	b/a/b/s:a	(Lb/at;)Lb/at;
    //   2527: pop
    //   2528: aload 17
    //   2530: aload_1
    //   2531: invokeinterface 527 1 0
    //   2536: putfield 524	b/a/b/s:q	Lb/a/b/a;
    //   2539: goto -56 -> 2483
    //   2542: aload 18
    //   2544: invokeinterface 532 1 0
    //   2549: astore 19
    //   2551: aload 16
    //   2553: astore_1
    //   2554: aload 19
    //   2556: ifnull -51 -> 2505
    //   2559: new 534	b/a/b/q
    //   2562: dup
    //   2563: aload 17
    //   2565: aload 16
    //   2567: getfield 226	b/at:g	Lb/au;
    //   2570: invokevirtual 537	b/au:c	()Lc/h;
    //   2573: aload 18
    //   2575: aload 19
    //   2577: invokestatic 542	c/r:a	(Lc/x;)Lc/g;
    //   2580: invokespecial 545	b/a/b/q:<init>	(Lb/a/b/s;Lc/h;Lb/a/b/a;Lc/g;)V
    //   2583: astore_1
    //   2584: aload 16
    //   2586: invokevirtual 331	b/at:a	()Lb/as;
    //   2589: astore 18
    //   2591: aload 18
    //   2593: new 547	b/a/b/w
    //   2596: dup
    //   2597: aload 16
    //   2599: getfield 447	b/at:f	Lb/z;
    //   2602: aload_1
    //   2603: invokestatic 550	c/r:a	(Lc/y;)Lc/h;
    //   2606: invokespecial 553	b/a/b/w:<init>	(Lb/z;Lc/h;)V
    //   2609: putfield 258	b/as:g	Lb/au;
    //   2612: aload 18
    //   2614: invokevirtual 259	b/as:a	()Lb/at;
    //   2617: astore_1
    //   2618: goto -113 -> 2505
    //   2621: aload_1
    //   2622: getfield 268	b/a/b/aa:b	Ljava/io/IOException;
    //   2625: athrow
    //   2626: aload_1
    //   2627: athrow
    //   2628: aload_1
    //   2629: getfield 262	b/a/b/s:l	Lb/at;
    //   2632: astore 17
    //   2634: aload_0
    //   2635: getfield 85	b/am:e	Lb/a/b/s;
    //   2638: astore 16
    //   2640: aload 16
    //   2642: getfield 262	b/a/b/s:l	Lb/at;
    //   2645: ifnonnull +11 -> 2656
    //   2648: new 105	java/lang/IllegalStateException
    //   2651: dup
    //   2652: invokespecial 106	java/lang/IllegalStateException:<init>	()V
    //   2655: athrow
    //   2656: aload 16
    //   2658: getfield 389	b/a/b/s:c	Lb/a/b/ad;
    //   2661: invokevirtual 556	b/a/b/ad:b	()Lb/a/c/c;
    //   2664: astore_1
    //   2665: aload_1
    //   2666: ifnull +134 -> 2800
    //   2669: aload_1
    //   2670: invokeinterface 561 1 0
    //   2675: astore_1
    //   2676: aload 16
    //   2678: getfield 262	b/a/b/s:l	Lb/at;
    //   2681: getfield 451	b/at:c	I
    //   2684: istore_3
    //   2685: aload 16
    //   2687: getfield 119	b/a/b/s:i	Lb/ao;
    //   2690: getfield 378	b/ao:b	Ljava/lang/String;
    //   2693: astore 18
    //   2695: iload_3
    //   2696: lookupswitch	default:+84->2780, 300:+190->2886, 301:+190->2886, 302:+190->2886, 303:+190->2886, 307:+168->2864, 308:+168->2864, 401:+151->2847, 407:+109->2805, 408:+381->3077
    //   2780: aconst_null
    //   2781: astore_1
    //   2782: aload_1
    //   2783: ifnonnull +341 -> 3124
    //   2786: iload_2
    //   2787: ifne +10 -> 2797
    //   2790: aload_0
    //   2791: getfield 85	b/am:e	Lb/a/b/s;
    //   2794: invokevirtual 89	b/a/b/s:b	()V
    //   2797: aload 17
    //   2799: areturn
    //   2800: aconst_null
    //   2801: astore_1
    //   2802: goto -126 -> 2676
    //   2805: aload_1
    //   2806: ifnull +29 -> 2835
    //   2809: aload_1
    //   2810: getfield 566	b/av:b	Ljava/net/Proxy;
    //   2813: astore_1
    //   2814: aload_1
    //   2815: invokevirtual 572	java/net/Proxy:type	()Ljava/net/Proxy$Type;
    //   2818: getstatic 578	java/net/Proxy$Type:HTTP	Ljava/net/Proxy$Type;
    //   2821: if_acmpeq +26 -> 2847
    //   2824: new 580	java/net/ProtocolException
    //   2827: dup
    //   2828: ldc_w 582
    //   2831: invokespecial 583	java/net/ProtocolException:<init>	(Ljava/lang/String;)V
    //   2834: athrow
    //   2835: aload 16
    //   2837: getfield 145	b/a/b/s:b	Lb/ai;
    //   2840: getfield 584	b/ai:b	Ljava/net/Proxy;
    //   2843: astore_1
    //   2844: goto -30 -> 2814
    //   2847: aload 16
    //   2849: getfield 145	b/a/b/s:b	Lb/ai;
    //   2852: getfield 587	b/ai:q	Lb/c;
    //   2855: invokeinterface 590 1 0
    //   2860: astore_1
    //   2861: goto -79 -> 2782
    //   2864: aload 18
    //   2866: ldc_w 380
    //   2869: invokevirtual 386	java/lang/String:equals	(Ljava/lang/Object;)Z
    //   2872: ifne +14 -> 2886
    //   2875: aload 18
    //   2877: ldc_w 592
    //   2880: invokevirtual 386	java/lang/String:equals	(Ljava/lang/Object;)Z
    //   2883: ifeq -103 -> 2780
    //   2886: aload 16
    //   2888: getfield 145	b/a/b/s:b	Lb/ai;
    //   2891: getfield 595	b/ai:u	Z
    //   2894: ifeq -114 -> 2780
    //   2897: aload 16
    //   2899: getfield 262	b/a/b/s:l	Lb/at;
    //   2902: ldc_w 597
    //   2905: invokevirtual 598	b/at:a	(Ljava/lang/String;)Ljava/lang/String;
    //   2908: astore_1
    //   2909: aload_1
    //   2910: ifnull -130 -> 2780
    //   2913: aload 16
    //   2915: getfield 119	b/a/b/s:i	Lb/ao;
    //   2918: getfield 127	b/ao:a	Lb/ac;
    //   2921: aload_1
    //   2922: invokevirtual 601	b/ac:c	(Ljava/lang/String;)Lb/ac;
    //   2925: astore_1
    //   2926: aload_1
    //   2927: ifnull -147 -> 2780
    //   2930: aload_1
    //   2931: getfield 603	b/ac:a	Ljava/lang/String;
    //   2934: aload 16
    //   2936: getfield 119	b/a/b/s:i	Lb/ao;
    //   2939: getfield 127	b/ao:a	Lb/ac;
    //   2942: getfield 603	b/ac:a	Ljava/lang/String;
    //   2945: invokevirtual 386	java/lang/String:equals	(Ljava/lang/Object;)Z
    //   2948: ifne +14 -> 2962
    //   2951: aload 16
    //   2953: getfield 145	b/a/b/s:b	Lb/ai;
    //   2956: getfield 606	b/ai:t	Z
    //   2959: ifeq -179 -> 2780
    //   2962: aload 16
    //   2964: getfield 119	b/a/b/s:i	Lb/ao;
    //   2967: invokevirtual 40	b/ao:a	()Lb/an;
    //   2970: astore 19
    //   2972: aload 18
    //   2974: invokestatic 611	b/a/b/t:b	(Ljava/lang/String;)Z
    //   2977: ifeq +53 -> 3030
    //   2980: aload 18
    //   2982: ldc_w 613
    //   2985: invokevirtual 386	java/lang/String:equals	(Ljava/lang/Object;)Z
    //   2988: ifne +73 -> 3061
    //   2991: iconst_1
    //   2992: istore_3
    //   2993: iload_3
    //   2994: ifeq +72 -> 3066
    //   2997: aload 19
    //   2999: ldc_w 380
    //   3002: invokevirtual 615	b/an:b	(Ljava/lang/String;)Lb/an;
    //   3005: pop
    //   3006: aload 19
    //   3008: ldc 72
    //   3010: invokevirtual 75	b/an:a	(Ljava/lang/String;)Lb/an;
    //   3013: pop
    //   3014: aload 19
    //   3016: ldc 65
    //   3018: invokevirtual 75	b/an:a	(Ljava/lang/String;)Lb/an;
    //   3021: pop
    //   3022: aload 19
    //   3024: ldc 47
    //   3026: invokevirtual 75	b/an:a	(Ljava/lang/String;)Lb/an;
    //   3029: pop
    //   3030: aload 16
    //   3032: aload_1
    //   3033: invokevirtual 618	b/a/b/s:a	(Lb/ac;)Z
    //   3036: ifne +12 -> 3048
    //   3039: aload 19
    //   3041: ldc_w 620
    //   3044: invokevirtual 75	b/an:a	(Ljava/lang/String;)Lb/an;
    //   3047: pop
    //   3048: aload 19
    //   3050: aload_1
    //   3051: invokevirtual 623	b/an:a	(Lb/ac;)Lb/an;
    //   3054: invokevirtual 78	b/an:a	()Lb/ao;
    //   3057: astore_1
    //   3058: goto -276 -> 2782
    //   3061: iconst_0
    //   3062: istore_3
    //   3063: goto -70 -> 2993
    //   3066: aload 19
    //   3068: aload 18
    //   3070: invokevirtual 615	b/an:b	(Ljava/lang/String;)Lb/an;
    //   3073: pop
    //   3074: goto -68 -> 3006
    //   3077: aload 16
    //   3079: getfield 417	b/a/b/s:m	Lc/x;
    //   3082: ifnull +14 -> 3096
    //   3085: aload 16
    //   3087: getfield 417	b/a/b/s:m	Lc/x;
    //   3090: instanceof 432
    //   3093: ifeq +26 -> 3119
    //   3096: iconst_1
    //   3097: istore_3
    //   3098: aload 16
    //   3100: getfield 412	b/a/b/s:o	Z
    //   3103: ifeq +7 -> 3110
    //   3106: iload_3
    //   3107: ifeq -327 -> 2780
    //   3110: aload 16
    //   3112: getfield 119	b/a/b/s:i	Lb/ao;
    //   3115: astore_1
    //   3116: goto -334 -> 2782
    //   3119: iconst_0
    //   3120: istore_3
    //   3121: goto -23 -> 3098
    //   3124: aload_0
    //   3125: getfield 85	b/am:e	Lb/a/b/s;
    //   3128: invokevirtual 112	b/a/b/s:c	()Lb/a/b/ad;
    //   3131: astore 16
    //   3133: iload 4
    //   3135: iconst_1
    //   3136: iadd
    //   3137: istore 4
    //   3139: iload 4
    //   3141: bipush 20
    //   3143: if_icmple +34 -> 3177
    //   3146: aload 16
    //   3148: invokevirtual 116	b/a/b/ad:c	()V
    //   3151: new 580	java/net/ProtocolException
    //   3154: dup
    //   3155: new 357	java/lang/StringBuilder
    //   3158: dup
    //   3159: ldc_w 625
    //   3162: invokespecial 626	java/lang/StringBuilder:<init>	(Ljava/lang/String;)V
    //   3165: iload 4
    //   3167: invokevirtual 630	java/lang/StringBuilder:append	(I)Ljava/lang/StringBuilder;
    //   3170: invokevirtual 362	java/lang/StringBuilder:toString	()Ljava/lang/String;
    //   3173: invokespecial 583	java/net/ProtocolException:<init>	(Ljava/lang/String;)V
    //   3176: athrow
    //   3177: aload_0
    //   3178: getfield 85	b/am:e	Lb/a/b/s;
    //   3181: aload_1
    //   3182: getfield 127	b/ao:a	Lb/ac;
    //   3185: invokevirtual 618	b/a/b/s:a	(Lb/ac;)Z
    //   3188: ifne +38 -> 3226
    //   3191: aload 16
    //   3193: invokevirtual 116	b/a/b/ad:c	()V
    //   3196: aconst_null
    //   3197: astore 16
    //   3199: aload_0
    //   3200: new 80	b/a/b/s
    //   3203: dup
    //   3204: aload_0
    //   3205: getfield 22	b/am:a	Lb/ai;
    //   3208: aload_1
    //   3209: iconst_0
    //   3210: iconst_0
    //   3211: iload_2
    //   3212: aload 16
    //   3214: aconst_null
    //   3215: aload 17
    //   3217: invokespecial 83	b/a/b/s:<init>	(Lb/ai;Lb/ao;ZZZLb/a/b/ad;Lb/a/b/z;Lb/at;)V
    //   3220: putfield 85	b/am:e	Lb/a/b/s;
    //   3223: goto -3118 -> 105
    //   3226: goto -27 -> 3199
    //   3229: lconst_0
    //   3230: lstore 8
    //   3232: goto -2250 -> 982
    //   3235: goto -2276 -> 959
    //   3238: goto -3158 -> 80
    //   3241: lconst_0
    //   3242: lstore 6
    //   3244: goto -2403 -> 841
    //   3247: lconst_0
    //   3248: lstore 6
    //   3250: goto -2319 -> 931
    //   3253: lconst_0
    //   3254: lstore 6
    //   3256: goto -2325 -> 931
    //   3259: iconst_0
    //   3260: istore_3
    //   3261: goto -2143 -> 1118
    //   3264: iconst_0
    //   3265: istore_3
    //   3266: goto -1390 -> 1876
    // Local variable table:
    //   start	length	slot	name	signature
    //   0	3269	0	this	am
    //   0	3269	1	paramao	ao
    //   0	3269	2	paramBoolean	boolean
    //   186	3080	3	i	int
    //   103	3063	4	j	int
    //   1550	147	5	bool	boolean
    //   45	3210	6	l1	long
    //   843	2388	8	l2	long
    //   996	49	10	l3	long
    //   983	23	12	l4	long
    //   899	186	14	l5	long
    //   4	3209	16	localObject1	Object
    //   21	3195	17	localObject2	Object
    //   152	2917	18	localObject3	Object
    //   346	2721	19	localObject4	Object
    //   386	1046	20	localb	b.a.b.b
    //   1305	12	21	localStringBuilder	StringBuilder
    // Exception table:
    //   from	to	target	type
    //   148	178	178	b/a/b/x
    //   203	240	178	b/a/b/x
    //   240	259	178	b/a/b/x
    //   259	284	178	b/a/b/x
    //   284	322	178	b/a/b/x
    //   322	341	178	b/a/b/x
    //   341	360	178	b/a/b/x
    //   364	372	178	b/a/b/x
    //   372	411	178	b/a/b/x
    //   414	421	178	b/a/b/x
    //   424	450	178	b/a/b/x
    //   450	483	178	b/a/b/x
    //   488	504	178	b/a/b/x
    //   504	586	178	b/a/b/x
    //   586	627	178	b/a/b/x
    //   667	704	178	b/a/b/x
    //   732	763	178	b/a/b/x
    //   766	795	178	b/a/b/x
    //   795	810	178	b/a/b/x
    //   813	841	178	b/a/b/x
    //   845	873	178	b/a/b/x
    //   873	931	178	b/a/b/x
    //   931	959	178	b/a/b/x
    //   959	982	178	b/a/b/x
    //   985	994	178	b/a/b/x
    //   998	1005	178	b/a/b/x
    //   1009	1032	178	b/a/b/x
    //   1032	1039	178	b/a/b/x
    //   1053	1062	178	b/a/b/x
    //   1073	1084	178	b/a/b/x
    //   1093	1116	178	b/a/b/x
    //   1122	1133	178	b/a/b/x
    //   1133	1147	178	b/a/b/x
    //   1150	1176	178	b/a/b/x
    //   1176	1189	178	b/a/b/x
    //   1206	1213	178	b/a/b/x
    //   1216	1243	178	b/a/b/x
    //   1249	1267	178	b/a/b/x
    //   1267	1280	178	b/a/b/x
    //   1287	1295	178	b/a/b/x
    //   1298	1322	178	b/a/b/x
    //   1325	1332	178	b/a/b/x
    //   1335	1365	178	b/a/b/x
    //   1365	1392	178	b/a/b/x
    //   1395	1416	178	b/a/b/x
    //   1419	1440	178	b/a/b/x
    //   1443	1454	178	b/a/b/x
    //   1457	1529	178	b/a/b/x
    //   1685	1693	178	b/a/b/x
    //   1693	1695	178	b/a/b/x
    //   1803	1834	178	b/a/b/x
    //   1834	1840	178	b/a/b/x
    //   1840	1874	178	b/a/b/x
    //   1880	2005	178	b/a/b/x
    //   2025	2057	178	b/a/b/x
    //   2060	2097	178	b/a/b/x
    //   2097	2177	178	b/a/b/x
    //   2177	2192	178	b/a/b/x
    //   2192	2218	178	b/a/b/x
    //   2218	2247	178	b/a/b/x
    //   2250	2260	178	b/a/b/x
    //   2263	2276	178	b/a/b/x
    //   2281	2293	178	b/a/b/x
    //   2298	2312	178	b/a/b/x
    //   2317	2328	178	b/a/b/x
    //   2328	2406	178	b/a/b/x
    //   2410	2483	178	b/a/b/x
    //   2483	2497	178	b/a/b/x
    //   2505	2516	178	b/a/b/x
    //   2519	2539	178	b/a/b/x
    //   2542	2551	178	b/a/b/x
    //   2559	2618	178	b/a/b/x
    //   148	178	184	finally
    //   179	184	184	finally
    //   203	240	184	finally
    //   240	259	184	finally
    //   259	284	184	finally
    //   284	322	184	finally
    //   322	341	184	finally
    //   341	360	184	finally
    //   364	372	184	finally
    //   372	411	184	finally
    //   414	421	184	finally
    //   424	450	184	finally
    //   450	483	184	finally
    //   488	504	184	finally
    //   504	586	184	finally
    //   586	627	184	finally
    //   628	641	184	finally
    //   667	704	184	finally
    //   708	718	184	finally
    //   732	763	184	finally
    //   766	795	184	finally
    //   795	810	184	finally
    //   813	841	184	finally
    //   845	873	184	finally
    //   873	931	184	finally
    //   931	959	184	finally
    //   959	982	184	finally
    //   985	994	184	finally
    //   998	1005	184	finally
    //   1009	1032	184	finally
    //   1032	1039	184	finally
    //   1053	1062	184	finally
    //   1073	1084	184	finally
    //   1093	1116	184	finally
    //   1122	1133	184	finally
    //   1133	1147	184	finally
    //   1150	1176	184	finally
    //   1176	1189	184	finally
    //   1206	1213	184	finally
    //   1216	1243	184	finally
    //   1249	1267	184	finally
    //   1267	1280	184	finally
    //   1287	1295	184	finally
    //   1298	1322	184	finally
    //   1325	1332	184	finally
    //   1335	1365	184	finally
    //   1365	1392	184	finally
    //   1395	1416	184	finally
    //   1419	1440	184	finally
    //   1443	1454	184	finally
    //   1457	1529	184	finally
    //   1685	1693	184	finally
    //   1693	1695	184	finally
    //   1803	1834	184	finally
    //   1834	1840	184	finally
    //   1840	1874	184	finally
    //   1880	2005	184	finally
    //   2025	2057	184	finally
    //   2060	2097	184	finally
    //   2097	2177	184	finally
    //   2177	2192	184	finally
    //   2192	2218	184	finally
    //   2218	2247	184	finally
    //   2250	2260	184	finally
    //   2263	2276	184	finally
    //   2281	2293	184	finally
    //   2298	2312	184	finally
    //   2317	2328	184	finally
    //   2328	2406	184	finally
    //   2410	2483	184	finally
    //   2483	2497	184	finally
    //   2505	2516	184	finally
    //   2519	2539	184	finally
    //   2542	2551	184	finally
    //   2559	2618	184	finally
    //   2621	2626	184	finally
    //   2626	2628	184	finally
    //   148	178	627	b/a/b/aa
    //   203	240	627	b/a/b/aa
    //   240	259	627	b/a/b/aa
    //   259	284	627	b/a/b/aa
    //   284	322	627	b/a/b/aa
    //   322	341	627	b/a/b/aa
    //   341	360	627	b/a/b/aa
    //   364	372	627	b/a/b/aa
    //   372	411	627	b/a/b/aa
    //   414	421	627	b/a/b/aa
    //   424	450	627	b/a/b/aa
    //   450	483	627	b/a/b/aa
    //   488	504	627	b/a/b/aa
    //   504	586	627	b/a/b/aa
    //   586	627	627	b/a/b/aa
    //   667	704	627	b/a/b/aa
    //   732	763	627	b/a/b/aa
    //   766	795	627	b/a/b/aa
    //   795	810	627	b/a/b/aa
    //   813	841	627	b/a/b/aa
    //   845	873	627	b/a/b/aa
    //   873	931	627	b/a/b/aa
    //   931	959	627	b/a/b/aa
    //   959	982	627	b/a/b/aa
    //   985	994	627	b/a/b/aa
    //   998	1005	627	b/a/b/aa
    //   1009	1032	627	b/a/b/aa
    //   1032	1039	627	b/a/b/aa
    //   1053	1062	627	b/a/b/aa
    //   1073	1084	627	b/a/b/aa
    //   1093	1116	627	b/a/b/aa
    //   1122	1133	627	b/a/b/aa
    //   1133	1147	627	b/a/b/aa
    //   1150	1176	627	b/a/b/aa
    //   1176	1189	627	b/a/b/aa
    //   1206	1213	627	b/a/b/aa
    //   1216	1243	627	b/a/b/aa
    //   1249	1267	627	b/a/b/aa
    //   1267	1280	627	b/a/b/aa
    //   1287	1295	627	b/a/b/aa
    //   1298	1322	627	b/a/b/aa
    //   1325	1332	627	b/a/b/aa
    //   1335	1365	627	b/a/b/aa
    //   1365	1392	627	b/a/b/aa
    //   1395	1416	627	b/a/b/aa
    //   1419	1440	627	b/a/b/aa
    //   1443	1454	627	b/a/b/aa
    //   1457	1529	627	b/a/b/aa
    //   1685	1693	627	b/a/b/aa
    //   1693	1695	627	b/a/b/aa
    //   1803	1834	627	b/a/b/aa
    //   1834	1840	627	b/a/b/aa
    //   1840	1874	627	b/a/b/aa
    //   1880	2005	627	b/a/b/aa
    //   2025	2057	627	b/a/b/aa
    //   2060	2097	627	b/a/b/aa
    //   2097	2177	627	b/a/b/aa
    //   2177	2192	627	b/a/b/aa
    //   2192	2218	627	b/a/b/aa
    //   2218	2247	627	b/a/b/aa
    //   2250	2260	627	b/a/b/aa
    //   2263	2276	627	b/a/b/aa
    //   2281	2293	627	b/a/b/aa
    //   2298	2312	627	b/a/b/aa
    //   2317	2328	627	b/a/b/aa
    //   2328	2406	627	b/a/b/aa
    //   2410	2483	627	b/a/b/aa
    //   2483	2497	627	b/a/b/aa
    //   2505	2516	627	b/a/b/aa
    //   2519	2539	627	b/a/b/aa
    //   2542	2551	627	b/a/b/aa
    //   2559	2618	627	b/a/b/aa
    //   646	652	655	finally
    //   723	729	655	finally
    //   148	178	707	java/io/IOException
    //   203	240	707	java/io/IOException
    //   240	259	707	java/io/IOException
    //   259	284	707	java/io/IOException
    //   284	322	707	java/io/IOException
    //   322	341	707	java/io/IOException
    //   341	360	707	java/io/IOException
    //   364	372	707	java/io/IOException
    //   372	411	707	java/io/IOException
    //   414	421	707	java/io/IOException
    //   424	450	707	java/io/IOException
    //   450	483	707	java/io/IOException
    //   488	504	707	java/io/IOException
    //   504	586	707	java/io/IOException
    //   586	627	707	java/io/IOException
    //   667	704	707	java/io/IOException
    //   732	763	707	java/io/IOException
    //   766	795	707	java/io/IOException
    //   795	810	707	java/io/IOException
    //   813	841	707	java/io/IOException
    //   845	873	707	java/io/IOException
    //   873	931	707	java/io/IOException
    //   931	959	707	java/io/IOException
    //   959	982	707	java/io/IOException
    //   985	994	707	java/io/IOException
    //   998	1005	707	java/io/IOException
    //   1009	1032	707	java/io/IOException
    //   1032	1039	707	java/io/IOException
    //   1053	1062	707	java/io/IOException
    //   1073	1084	707	java/io/IOException
    //   1093	1116	707	java/io/IOException
    //   1122	1133	707	java/io/IOException
    //   1133	1147	707	java/io/IOException
    //   1150	1176	707	java/io/IOException
    //   1176	1189	707	java/io/IOException
    //   1206	1213	707	java/io/IOException
    //   1216	1243	707	java/io/IOException
    //   1249	1267	707	java/io/IOException
    //   1267	1280	707	java/io/IOException
    //   1287	1295	707	java/io/IOException
    //   1298	1322	707	java/io/IOException
    //   1325	1332	707	java/io/IOException
    //   1335	1365	707	java/io/IOException
    //   1365	1392	707	java/io/IOException
    //   1395	1416	707	java/io/IOException
    //   1419	1440	707	java/io/IOException
    //   1443	1454	707	java/io/IOException
    //   1457	1529	707	java/io/IOException
    //   1685	1693	707	java/io/IOException
    //   1693	1695	707	java/io/IOException
    //   1803	1834	707	java/io/IOException
    //   1834	1840	707	java/io/IOException
    //   1840	1874	707	java/io/IOException
    //   1880	2005	707	java/io/IOException
    //   2025	2057	707	java/io/IOException
    //   2060	2097	707	java/io/IOException
    //   2097	2177	707	java/io/IOException
    //   2177	2192	707	java/io/IOException
    //   2192	2218	707	java/io/IOException
    //   2218	2247	707	java/io/IOException
    //   2250	2260	707	java/io/IOException
    //   2263	2276	707	java/io/IOException
    //   2281	2293	707	java/io/IOException
    //   2298	2312	707	java/io/IOException
    //   2317	2328	707	java/io/IOException
    //   2328	2406	707	java/io/IOException
    //   2410	2483	707	java/io/IOException
    //   2483	2497	707	java/io/IOException
    //   2505	2516	707	java/io/IOException
    //   2519	2539	707	java/io/IOException
    //   2542	2551	707	java/io/IOException
    //   2559	2618	707	java/io/IOException
    //   1532	1549	1679	finally
    //   1552	1638	1679	finally
    //   1644	1659	1679	finally
    //   1668	1679	1679	finally
    //   1715	1745	1679	finally
    //   1748	1760	1679	finally
    //   1763	1800	1679	finally
  }
}

/* Location:
 * Qualified Name:     b.am
 * Java Class Version: 6 (50.0)
 * JD-Core Version:    0.7.1
 */